[{"timestamp_utc":"2024-01-11T15:19:02.195Z","context_time":1704986342195,"message_context_uri":"spotify:playlist:37i9dQZEVXbkoSs7u90Cw1","message_is_made_for_user":true,"message_registration_country":"AE","message_track_uris":["spotify:track:5aeXimPjlHeqI7W7hJIqlo","spotify:track:0kMpRZWiwAdum2eQejAxMN","spotify:track:3CMdlCNPXJZXouXZHKhYyV","spotify:track:1NMYbsFZyxwHRNaLGzFGWh","spotify:track:48H87I4tgT2V5n7ZDYXGPn","spotify:track:2DaPCl392tphoi2TqslBdG","spotify:track:1txUL9NNB7bbWYDLCaN4KV","spotify:track:1iTuo6oMChhXAgu2LCFUiz","spotify:track:6R417VYcuf4lNMg6dT1ueV","spotify:track:1UrEASMdC7chHBizGbpAyx","spotify:track:3lJOVcAw0GldtMbrZtuMeS","spotify:track:3CkKFRGxteb3TBCNmZy5LB","spotify:track:4eSrby5sF3zwEgE3mGXJYV","spotify:track:20z7Q3CO1gRP2Yb8UhIQdq","spotify:track:7EqH9On4VEdHFhiu5DdFzP","spotify:track:10jkTly01YHd0Jm2xUtFlB","spotify:track:1yxTbuOoym1Dx56OeTyQEB","spotify:track:0wvBwIlOv5Ze5jTB4EeBPg","spotify:track:3bE5E0AGPyHvmmA9LNoi5t","spotify:track:64iqTKzDkiuhQ1JCjMUsBr","spotify:track:4aEv1igs7UqxBEHdicIcZV","spotify:track:1b9VHDd6FJEzd7ecSHZj1S","spotify:track:0Ja4AAjauZDRquEz7scXut","spotify:track:045w0V7APk1jYTnd0OHdTx","spotify:track:0Nz23ikouHjjqmw6VDMXA6","spotify:track:0hN3gqhsyQryxyfUwbsAJY","spotify:track:2oVHoIWuMqI5NVz6WYn7Hz","spotify:track:25yA3k7cBNDqejRJUun4Qe","spotify:track:1d3YFxKWh1Rx9y2sJJ9Jd2","spotify:track:2PC92mpsc0XCCILU85Dlvz"]},{"timestamp_utc":"2024-01-03T15:26:31.919Z","context_time":1704295591919,"message_context_uri":"spotify:playlist:37i9dQZEVXbkoSs7u90Cw1","message_is_made_for_user":true,"message_registration_country":"AE","message_track_uris":["spotify:track:2DaPCl392tphoi2TqslBdG","spotify:track:1txUL9NNB7bbWYDLCaN4KV","spotify:track:1iTuo6oMChhXAgu2LCFUiz","spotify:track:6R417VYcuf4lNMg6dT1ueV","spotify:track:1UrEASMdC7chHBizGbpAyx","spotify:track:6oRkOFfxvJ9KMopWbtd4D8","spotify:track:4eSrby5sF3zwEgE3mGXJYV","spotify:track:6M1B4hA3YNbMgkugKErPxV","spotify:track:7EqH9On4VEdHFhiu5DdFzP","spotify:track:3iFYJMrRS0fLrwDNVbqNF0","spotify:track:77B8mI3PW8x2ke5UIyevDl","spotify:track:10jkTly01YHd0Jm2xUtFlB","spotify:track:1yxTbuOoym1Dx56OeTyQEB","spotify:track:0wvBwIlOv5Ze5jTB4EeBPg","spotify:track:1b9VHDd6FJEzd7ecSHZj1S","spotify:track:6dwS1tgnir4zmbgburrUsA","spotify:track:0Ja4AAjauZDRquEz7scXut","spotify:track:0Nz23ikouHjjqmw6VDMXA6","spotify:track:0hN3gqhsyQryxyfUwbsAJY","spotify:track:25yA3k7cBNDqejRJUun4Qe","spotify:track:2oVHoIWuMqI5NVz6WYn7Hz","spotify:track:3Symf7eRIlddMJNXtbA6IK","spotify:track:5dvPoqBSwHiFR0uGBppPYQ","spotify:track:2PC92mpsc0XCCILU85Dlvz","spotify:track:3L5n8FHAe9RCsrKDSDbU0t","spotify:track:7nrVOGH5g2XbCcVIPc1z2v","spotify:track:4g8BvKyw10b20zfYS3LnoL","spotify:track:4WfGDkm99oLJSAtELYZYEd","spotify:track:4yagkb6nJCRcfjUhaOVHTw","spotify:track:7smWOsdOrLqq87a8sRN0PH"]},{"timestamp_utc":"2023-11-20T15:34:37.496Z","context_time":1700494477496,"message_context_uri":"spotify:playlist:37i9dQZEVXbkoSs7u90Cw1","message_is_made_for_user":true,"message_registration_country":"AE","message_track_uris":["spotify:track:1qSLt4bauTRIlLo0lw1U02","spotify:track:27xsLWmSmEAiXABnOngOw7","spotify:track:5oT4UO1LJMgnl26aIy88ox","spotify:track:1eKQFMKfCezCI1LF2oByEm","spotify:track:47IzfVVQs2orvksB1CGRvO","spotify:track:0gkQiwGIuneO08yaQ68HK5","spotify:track:0jqki4UKTXtSkyZjKiTUsi","spotify:track:4Q6S45dcKtAIBaGnGZ4yD6","spotify:track:3ZzUOWnQuNxenx2MbZqtYq","spotify:track:7q8RDjLprHOErgwz4ReQGA","spotify:track:50ISJbc0MNUxfzrhDg2k92","spotify:track:4m2af7wCfOyYLBQZ3l7xLs","spotify:track:0e9puAKZblpFaZyEZ0ZcJ6","spotify:track:322TvI9HYg7Tz2DizOAniw","spotify:track:2pgMykS4vRfWjCn3HBW7Sl","spotify:track:2m4s3761CzsYyH5lYoF4qu","spotify:track:1anIxQ7F0J7Ayc9QMNwkNB","spotify:track:0zboMHaQqZSc5g094rpR9j","spotify:track:5St1eVg5tOIK9HEmMJznLX","spotify:track:0Qo75eJMY72e5IQJt0Dz9z","spotify:track:2aj9isuH4NcbdNKJrOWMTs","spotify:track:0Q37Ax4ON1mIANcQvqfbOl","spotify:track:6qkwieeAuu97CLLtuooHd3","spotify:track:7JJOUjiewemzvDXbq0LcBY","spotify:track:51h7YmJJp0FSM6AyFycRJ2","spotify:track:6bpQvYciF8jtaaXrGV6AKp","spotify:track:3n3TDfjL4RD8sC8ZOakgkW","spotify:track:4bWN06wez00SFofUjnvLfG","spotify:track:72DQsnQrsEwfgTgaqRzahu","spotify:track:3DNluh1hzpBIwIhMNAhN3V"]},{"timestamp_utc":"2024-02-06T05:28:38.839Z","context_time":1707197318839,"message_context_uri":"spotify:playlist:37i9dQZEVXbkoSs7u90Cw1","message_is_made_for_user":true,"message_registration_country":"AE","message_track_uris":["spotify:track:6PNhbEHabSERm2YHXOSizH","spotify:track:4m47o25mr9RqvOUzfRyjy3","spotify:track:2PCkD2ZI7zf0LOWdH2gNz5","spotify:track:5Msv4zzbXHxK0TzlAySK1J","spotify:track:5t36KLDvhjsIaat1DDxrDo","spotify:track:2usXJTfTSRH5ajx7uLnBfQ","spotify:track:2edUKbpj6GxgViPiL5EbIq","spotify:track:1QBMPnuR6v9OB1VVxgJB5G","spotify:track:1aooH2O4Y2neJ1aIZZOAml","spotify:track:047lJsrqwXM73t5a1iSF2B","spotify:track:6BfILljHPy6KB2W8Yp0Dr0","spotify:track:5eB2NeY2Px3EgzIsizedZe","spotify:track:3UxSyVzUrRxG3VyNNWWt7u","spotify:track:3wysCwuzcaaPGEibqnU3nz","spotify:track:2mtCcdlsA2q4CNzVWxlyxi","spotify:track:6F9zM0nqQE9OOsMGIPEQMD","spotify:track:6fMZ7g4JvGCRgLldIxi6Sl","spotify:track:753yGdIWiuZUn1cDRJziT7","spotify:track:6RaNwx66fRVaj07kZZWwV5","spotify:track:2IzKfxGPk9hbJdGJhZWIAb","spotify:track:5gPRX0AmXth8OKLJ0QuKae","spotify:track:7qn2DjVZipJEJ5h0p1HvSL","spotify:track:493n4dFutqZNQugLgPuQ1p","spotify:track:48TbjAwxnglZJzeEj7r3jv","spotify:track:0U8xGuKNtRz2PWVGaLjJ8V","spotify:track:4smqvcyz6mp27zNIUnLuvV","spotify:track:7lzPCtx5j2JRFhbsGpbzQ7","spotify:track:38uKHamvGkT14HDIGo5cOv","spotify:track:3EJslhR33350RLGMb6eOAg","spotify:track:387j61utwXNE7Bvi5UTR2k"]},{"timestamp_utc":"2023-11-19T20:19:22.813Z","context_time":1700425162813,"message_context_uri":"spotify:playlist:37i9dQZEVXbkoSs7u90Cw1","message_is_made_for_user":true,"message_registration_country":"AE","message_track_uris":["spotify:track:1qSLt4bauTRIlLo0lw1U02","spotify:track:27xsLWmSmEAiXABnOngOw7","spotify:track:5oT4UO1LJMgnl26aIy88ox","spotify:track:1eKQFMKfCezCI1LF2oByEm","spotify:track:47IzfVVQs2orvksB1CGRvO","spotify:track:0gkQiwGIuneO08yaQ68HK5","spotify:track:0jqki4UKTXtSkyZjKiTUsi","spotify:track:4Q6S45dcKtAIBaGnGZ4yD6","spotify:track:3ZzUOWnQuNxenx2MbZqtYq","spotify:track:7q8RDjLprHOErgwz4ReQGA","spotify:track:50ISJbc0MNUxfzrhDg2k92","spotify:track:4m2af7wCfOyYLBQZ3l7xLs","spotify:track:0e9puAKZblpFaZyEZ0ZcJ6","spotify:track:322TvI9HYg7Tz2DizOAniw","spotify:track:2pgMykS4vRfWjCn3HBW7Sl","spotify:track:2m4s3761CzsYyH5lYoF4qu","spotify:track:1anIxQ7F0J7Ayc9QMNwkNB","spotify:track:0zboMHaQqZSc5g094rpR9j","spotify:track:5St1eVg5tOIK9HEmMJznLX","spotify:track:0Qo75eJMY72e5IQJt0Dz9z","spotify:track:2aj9isuH4NcbdNKJrOWMTs","spotify:track:0Q37Ax4ON1mIANcQvqfbOl","spotify:track:6qkwieeAuu97CLLtuooHd3","spotify:track:7JJOUjiewemzvDXbq0LcBY","spotify:track:51h7YmJJp0FSM6AyFycRJ2","spotify:track:6bpQvYciF8jtaaXrGV6AKp","spotify:track:3n3TDfjL4RD8sC8ZOakgkW","spotify:track:4bWN06wez00SFofUjnvLfG","spotify:track:72DQsnQrsEwfgTgaqRzahu","spotify:track:3DNluh1hzpBIwIhMNAhN3V"]},{"timestamp_utc":"2023-11-14T14:36:06.033Z","context_time":1699972566033,"message_context_uri":"spotify:playlist:37i9dQZEVXbkoSs7u90Cw1","message_is_made_for_user":true,"message_registration_country":"AE","message_track_uris":["spotify:track:1eKQFMKfCezCI1LF2oByEm","spotify:track:0e9puAKZblpFaZyEZ0ZcJ6","spotify:track:322TvI9HYg7Tz2DizOAniw","spotify:track:65kga6DUIuueiZHR52tWcb","spotify:track:1anIxQ7F0J7Ayc9QMNwkNB","spotify:track:2pgMykS4vRfWjCn3HBW7Sl","spotify:track:2m4s3761CzsYyH5lYoF4qu","spotify:track:6qkwieeAuu97CLLtuooHd3","spotify:track:3n3TDfjL4RD8sC8ZOakgkW","spotify:track:6bpQvYciF8jtaaXrGV6AKp","spotify:track:3yHyiUDJdz02FZ6jfUbsmY","spotify:track:6vPFDbyzSYWAL7r3Waa7BZ","spotify:track:35ugbjNCcL0d39D1C5eyt4","spotify:track:18NWRHrL2xqGIw5SGSyf3S","spotify:track:6vB3eJU3ZOZXJxOKRcT2kl","spotify:track:3DNluh1hzpBIwIhMNAhN3V","spotify:track:5PlvEOKEO40fwk1qHXGuH0","spotify:track:1sZFDDmmBVkcHOpV6AB0Nx","spotify:track:6FahmzZYKH0zb2f9hrVsvw","spotify:track:2tb3BSK1Z9s5n7YynbuAbp","spotify:track:6SfLZ94X4nImZChgqmoP3q","spotify:track:0i7hmzHYai87aZzlKT7MhO","spotify:track:0nXYmY9YtiHkFGlR3cusur","spotify:track:4cbN08AlbNtanvMNhPVcPe","spotify:track:6p8DwAh6wJ7S6jmpyYlBYp","spotify:track:1REh5aFdSnrw06A67wpGk3","spotify:track:72vuBPMhwFNlSYpTSf6fVD","spotify:track:7eQBzDRjBJ2bCkRKxNPbXm","spotify:track:3gJFL7cF0ziqTjqcIMNqv3","spotify:track:6sQNYW4YycsO1c8uhZpdA2"]},{"timestamp_utc":"2023-11-21T03:46:30.805Z","context_time":1700538390805,"message_context_uri":"spotify:playlist:37i9dQZEVXbkoSs7u90Cw1","message_is_made_for_user":true,"message_registration_country":"AE","message_track_uris":["spotify:track:1qSLt4bauTRIlLo0lw1U02","spotify:track:27xsLWmSmEAiXABnOngOw7","spotify:track:5oT4UO1LJMgnl26aIy88ox","spotify:track:1eKQFMKfCezCI1LF2oByEm","spotify:track:47IzfVVQs2orvksB1CGRvO","spotify:track:0gkQiwGIuneO08yaQ68HK5","spotify:track:0jqki4UKTXtSkyZjKiTUsi","spotify:track:4Q6S45dcKtAIBaGnGZ4yD6","spotify:track:3ZzUOWnQuNxenx2MbZqtYq","spotify:track:7q8RDjLprHOErgwz4ReQGA","spotify:track:50ISJbc0MNUxfzrhDg2k92","spotify:track:4m2af7wCfOyYLBQZ3l7xLs","spotify:track:0e9puAKZblpFaZyEZ0ZcJ6","spotify:track:322TvI9HYg7Tz2DizOAniw","spotify:track:2pgMykS4vRfWjCn3HBW7Sl","spotify:track:2m4s3761CzsYyH5lYoF4qu","spotify:track:1anIxQ7F0J7Ayc9QMNwkNB","spotify:track:0zboMHaQqZSc5g094rpR9j","spotify:track:5St1eVg5tOIK9HEmMJznLX","spotify:track:0Qo75eJMY72e5IQJt0Dz9z","spotify:track:2aj9isuH4NcbdNKJrOWMTs","spotify:track:0Q37Ax4ON1mIANcQvqfbOl","spotify:track:6qkwieeAuu97CLLtuooHd3","spotify:track:7JJOUjiewemzvDXbq0LcBY","spotify:track:51h7YmJJp0FSM6AyFycRJ2","spotify:track:6bpQvYciF8jtaaXrGV6AKp","spotify:track:3n3TDfjL4RD8sC8ZOakgkW","spotify:track:4bWN06wez00SFofUjnvLfG","spotify:track:72DQsnQrsEwfgTgaqRzahu","spotify:track:3DNluh1hzpBIwIhMNAhN3V"]},{"timestamp_utc":"2023-12-25T07:53:05.547Z","context_time":1703490785547,"message_context_uri":"spotify:playlist:37i9dQZEVXbkoSs7u90Cw1","message_is_made_for_user":true,"message_registration_country":"AE","message_track_uris":["spotify:track:7EqH9On4VEdHFhiu5DdFzP","spotify:track:5Lvwzaf8BTuRDBmQ1GyeNA","spotify:track:3iFYJMrRS0fLrwDNVbqNF0","spotify:track:7kXRY7Tberw5S1iVLeYwmz","spotify:track:77B8mI3PW8x2ke5UIyevDl","spotify:track:1yxTbuOoym1Dx56OeTyQEB","spotify:track:0Ja4AAjauZDRquEz7scXut","spotify:track:0HMA7v4t7UaXonj9VmASAY","spotify:track:6oYQO84yM4ZrrOj9ssxDMl","spotify:track:0Nz23ikouHjjqmw6VDMXA6","spotify:track:0hN3gqhsyQryxyfUwbsAJY","spotify:track:25yA3k7cBNDqejRJUun4Qe","spotify:track:2oVHoIWuMqI5NVz6WYn7Hz","spotify:track:3Symf7eRIlddMJNXtbA6IK","spotify:track:5dvPoqBSwHiFR0uGBppPYQ","spotify:track:2PC92mpsc0XCCILU85Dlvz","spotify:track:3L5n8FHAe9RCsrKDSDbU0t","spotify:track:7nrVOGH5g2XbCcVIPc1z2v","spotify:track:74qIx2lHqfMB8SnlborPoG","spotify:track:4g8BvKyw10b20zfYS3LnoL","spotify:track:0jaX10A3R9z6iMdVrq6Xiz","spotify:track:3QX2xbfH8LDUaHIA5YQmtO","spotify:track:4WfGDkm99oLJSAtELYZYEd","spotify:track:4yagkb6nJCRcfjUhaOVHTw","spotify:track:4SmmoqGZXCido1Tcddy5cI","spotify:track:7smWOsdOrLqq87a8sRN0PH","spotify:track:7eKrZvt4uORY0DLABy7gMY","spotify:track:7lEQxb3JnTJcj2bHrP6kwH","spotify:track:1lvoAUC071648FyyvUjKLO","spotify:track:31VM3M27RYAbkLcx69pLsG"]},{"timestamp_utc":"2023-11-11T07:51:07.922Z","context_time":1699689067922,"message_context_uri":"spotify:playlist:37i9dQZEVXbkoSs7u90Cw1","message_is_made_for_user":true,"message_registration_country":"AE","message_track_uris":["spotify:track:65kga6DUIuueiZHR52tWcb","spotify:track:0Rs8QF1GrAar2X4pHRutmL","spotify:track:1anIxQ7F0J7Ayc9QMNwkNB","spotify:track:2pgMykS4vRfWjCn3HBW7Sl","spotify:track:2m4s3761CzsYyH5lYoF4qu","spotify:track:2FOzVtoTjalPbQpsvAVTTI","spotify:track:6qkwieeAuu97CLLtuooHd3","spotify:track:3n3TDfjL4RD8sC8ZOakgkW","spotify:track:6bpQvYciF8jtaaXrGV6AKp","spotify:track:3yHyiUDJdz02FZ6jfUbsmY","spotify:track:6vPFDbyzSYWAL7r3Waa7BZ","spotify:track:35ugbjNCcL0d39D1C5eyt4","spotify:track:18NWRHrL2xqGIw5SGSyf3S","spotify:track:6vB3eJU3ZOZXJxOKRcT2kl","spotify:track:3DNluh1hzpBIwIhMNAhN3V","spotify:track:1sZFDDmmBVkcHOpV6AB0Nx","spotify:track:6FahmzZYKH0zb2f9hrVsvw","spotify:track:5PlvEOKEO40fwk1qHXGuH0","spotify:track:1REh5aFdSnrw06A67wpGk3","spotify:track:2tb3BSK1Z9s5n7YynbuAbp","spotify:track:6SfLZ94X4nImZChgqmoP3q","spotify:track:4cbN08AlbNtanvMNhPVcPe","spotify:track:6p8DwAh6wJ7S6jmpyYlBYp","spotify:track:0nXYmY9YtiHkFGlR3cusur","spotify:track:0i7hmzHYai87aZzlKT7MhO","spotify:track:7eQBzDRjBJ2bCkRKxNPbXm","spotify:track:72vuBPMhwFNlSYpTSf6fVD","spotify:track:0VBdCcaY6ERYKF7fZXQ8YX","spotify:track:4EWPO9rKRv0orDRlYLnn4J","spotify:track:3gJFL7cF0ziqTjqcIMNqv3"]},{"timestamp_utc":"2023-12-21T13:40:03.149Z","context_time":1703166003149,"message_context_uri":"spotify:playlist:37i9dQZEVXbkoSs7u90Cw1","message_is_made_for_user":true,"message_registration_country":"AE","message_track_uris":["spotify:track:0Nz23ikouHjjqmw6VDMXA6","spotify:track:25yA3k7cBNDqejRJUun4Qe","spotify:track:0hN3gqhsyQryxyfUwbsAJY","spotify:track:2oVHoIWuMqI5NVz6WYn7Hz","spotify:track:5B8VpcIC3EAI3wke3XQoRy","spotify:track:5dvPoqBSwHiFR0uGBppPYQ","spotify:track:2PC92mpsc0XCCILU85Dlvz","spotify:track:3L5n8FHAe9RCsrKDSDbU0t","spotify:track:7nrVOGH5g2XbCcVIPc1z2v","spotify:track:74qIx2lHqfMB8SnlborPoG","spotify:track:4WfGDkm99oLJSAtELYZYEd","spotify:track:3QX2xbfH8LDUaHIA5YQmtO","spotify:track:4g8BvKyw10b20zfYS3LnoL","spotify:track:0jaX10A3R9z6iMdVrq6Xiz","spotify:track:4yagkb6nJCRcfjUhaOVHTw","spotify:track:4SmmoqGZXCido1Tcddy5cI","spotify:track:7smWOsdOrLqq87a8sRN0PH","spotify:track:5XMglV3BsTZyr97DC9yqIb","spotify:track:35FFqjqaPv1Fr9B1GtJdZO","spotify:track:4zNmisbCLIQLPlU1fcks0c","spotify:track:31VM3M27RYAbkLcx69pLsG","spotify:track:7eKrZvt4uORY0DLABy7gMY","spotify:track:1lvoAUC071648FyyvUjKLO","spotify:track:7lEQxb3JnTJcj2bHrP6kwH","spotify:track:4lYXywil8gd4a5shYzcJjP","spotify:track:1YzzGuqqfI71YEdNYPYIhO","spotify:track:7993rSSJhvymBDhq0WeDeE","spotify:track:38jz2nov1xFBOzsNE60u4a","spotify:track:6vzZxRUs3Zxg0HuLoqtt6c","spotify:track:04odGx95cXda5ykFx7Pj6w"]},{"timestamp_utc":"2023-11-27T14:35:32.110Z","context_time":1701095732110,"message_context_uri":"spotify:playlist:37i9dQZEVXbkoSs7u90Cw1","message_is_made_for_user":true,"message_registration_country":"AE","message_track_uris":["spotify:track:0a2NP8kiyBjKMKr9yBgmu9","spotify:track:6i3DBbjAzfZqbnqCND1hlX","spotify:track:04odGx95cXda5ykFx7Pj6w","spotify:track:7993rSSJhvymBDhq0WeDeE","spotify:track:38jz2nov1xFBOzsNE60u4a","spotify:track:6vzZxRUs3Zxg0HuLoqtt6c","spotify:track:207YcqxaFYsOdJarlqyjWl","spotify:track:23DBeqyrFvncQFf9jiuklR","spotify:track:1MiFS7YNfRcJCiI8y33RUe","spotify:track:1qSLt4bauTRIlLo0lw1U02","spotify:track:27xsLWmSmEAiXABnOngOw7","spotify:track:5oT4UO1LJMgnl26aIy88ox","spotify:track:44PrLucPgjbVvMAjpvMDCk","spotify:track:1eKQFMKfCezCI1LF2oByEm","spotify:track:47IzfVVQs2orvksB1CGRvO","spotify:track:25jISSHAd4q2CVTsO7EHJM","spotify:track:0gkQiwGIuneO08yaQ68HK5","spotify:track:2jm0UrP5A9ccJ3twMI8cVq","spotify:track:4Q6S45dcKtAIBaGnGZ4yD6","spotify:track:1B8g9FFMUDXlCpjJfiiT9D","spotify:track:3HnpI9mWSRtOdHBrJxuUlD","spotify:track:4pAd9xohEcZ1NzQD3S14pP","spotify:track:5dRD4iHgRS4yKWCh2pdqUV","spotify:track:7FJ5LdspkWcxPUkV8dzMOL","spotify:track:322TvI9HYg7Tz2DizOAniw","spotify:track:2pgMykS4vRfWjCn3HBW7Sl","spotify:track:1anIxQ7F0J7Ayc9QMNwkNB","spotify:track:3duI7TT4kzLtoqf4PeUR3Z","spotify:track:7JJOUjiewemzvDXbq0LcBY","spotify:track:51h7YmJJp0FSM6AyFycRJ2"]},{"timestamp_utc":"2023-11-22T04:10:53.393Z","context_time":1700626253393,"message_context_uri":"spotify:playlist:37i9dQZEVXbkoSs7u90Cw1","message_is_made_for_user":true,"message_registration_country":"AE","message_track_uris":["spotify:track:1qSLt4bauTRIlLo0lw1U02","spotify:track:27xsLWmSmEAiXABnOngOw7","spotify:track:5oT4UO1LJMgnl26aIy88ox","spotify:track:1eKQFMKfCezCI1LF2oByEm","spotify:track:47IzfVVQs2orvksB1CGRvO","spotify:track:0gkQiwGIuneO08yaQ68HK5","spotify:track:0jqki4UKTXtSkyZjKiTUsi","spotify:track:4Q6S45dcKtAIBaGnGZ4yD6","spotify:track:3ZzUOWnQuNxenx2MbZqtYq","spotify:track:7q8RDjLprHOErgwz4ReQGA","spotify:track:50ISJbc0MNUxfzrhDg2k92","spotify:track:4m2af7wCfOyYLBQZ3l7xLs","spotify:track:0e9puAKZblpFaZyEZ0ZcJ6","spotify:track:322TvI9HYg7Tz2DizOAniw","spotify:track:2pgMykS4vRfWjCn3HBW7Sl","spotify:track:2m4s3761CzsYyH5lYoF4qu","spotify:track:1anIxQ7F0J7Ayc9QMNwkNB","spotify:track:0zboMHaQqZSc5g094rpR9j","spotify:track:5St1eVg5tOIK9HEmMJznLX","spotify:track:0Qo75eJMY72e5IQJt0Dz9z","spotify:track:2aj9isuH4NcbdNKJrOWMTs","spotify:track:0Q37Ax4ON1mIANcQvqfbOl","spotify:track:6qkwieeAuu97CLLtuooHd3","spotify:track:7JJOUjiewemzvDXbq0LcBY","spotify:track:51h7YmJJp0FSM6AyFycRJ2","spotify:track:6bpQvYciF8jtaaXrGV6AKp","spotify:track:3n3TDfjL4RD8sC8ZOakgkW","spotify:track:4bWN06wez00SFofUjnvLfG","spotify:track:72DQsnQrsEwfgTgaqRzahu","spotify:track:3DNluh1hzpBIwIhMNAhN3V"]},{"timestamp_utc":"2024-02-02T19:18:27.354Z","context_time":1706901507354,"message_context_uri":"spotify:playlist:37i9dQZEVXbkoSs7u90Cw1","message_is_made_for_user":true,"message_registration_country":"AE","message_track_uris":["spotify:track:6PNhbEHabSERm2YHXOSizH","spotify:track:4m47o25mr9RqvOUzfRyjy3","spotify:track:2PCkD2ZI7zf0LOWdH2gNz5","spotify:track:5Msv4zzbXHxK0TzlAySK1J","spotify:track:5t36KLDvhjsIaat1DDxrDo","spotify:track:2usXJTfTSRH5ajx7uLnBfQ","spotify:track:2edUKbpj6GxgViPiL5EbIq","spotify:track:1QBMPnuR6v9OB1VVxgJB5G","spotify:track:1aooH2O4Y2neJ1aIZZOAml","spotify:track:047lJsrqwXM73t5a1iSF2B","spotify:track:6BfILljHPy6KB2W8Yp0Dr0","spotify:track:5eB2NeY2Px3EgzIsizedZe","spotify:track:3UxSyVzUrRxG3VyNNWWt7u","spotify:track:3wysCwuzcaaPGEibqnU3nz","spotify:track:2mtCcdlsA2q4CNzVWxlyxi","spotify:track:6F9zM0nqQE9OOsMGIPEQMD","spotify:track:753yGdIWiuZUn1cDRJziT7","spotify:track:6fMZ7g4JvGCRgLldIxi6Sl","spotify:track:6RaNwx66fRVaj07kZZWwV5","spotify:track:2IzKfxGPk9hbJdGJhZWIAb","spotify:track:0lv4nDnoa81qfc4QYWtOjQ","spotify:track:7qn2DjVZipJEJ5h0p1HvSL","spotify:track:493n4dFutqZNQugLgPuQ1p","spotify:track:48TbjAwxnglZJzeEj7r3jv","spotify:track:0U8xGuKNtRz2PWVGaLjJ8V","spotify:track:4smqvcyz6mp27zNIUnLuvV","spotify:track:7lzPCtx5j2JRFhbsGpbzQ7","spotify:track:38uKHamvGkT14HDIGo5cOv","spotify:track:3EJslhR33350RLGMb6eOAg","spotify:track:387j61utwXNE7Bvi5UTR2k"]},{"timestamp_utc":"2024-01-02T12:32:00.390Z","context_time":1704198720390,"message_context_uri":"spotify:playlist:37i9dQZEVXbkoSs7u90Cw1","message_is_made_for_user":true,"message_registration_country":"AE","message_track_uris":["spotify:track:2DaPCl392tphoi2TqslBdG","spotify:track:1txUL9NNB7bbWYDLCaN4KV","spotify:track:1iTuo6oMChhXAgu2LCFUiz","spotify:track:6R417VYcuf4lNMg6dT1ueV","spotify:track:1UrEASMdC7chHBizGbpAyx","spotify:track:6oRkOFfxvJ9KMopWbtd4D8","spotify:track:4eSrby5sF3zwEgE3mGXJYV","spotify:track:6M1B4hA3YNbMgkugKErPxV","spotify:track:7EqH9On4VEdHFhiu5DdFzP","spotify:track:3iFYJMrRS0fLrwDNVbqNF0","spotify:track:77B8mI3PW8x2ke5UIyevDl","spotify:track:10jkTly01YHd0Jm2xUtFlB","spotify:track:1yxTbuOoym1Dx56OeTyQEB","spotify:track:0wvBwIlOv5Ze5jTB4EeBPg","spotify:track:1b9VHDd6FJEzd7ecSHZj1S","spotify:track:6dwS1tgnir4zmbgburrUsA","spotify:track:0Ja4AAjauZDRquEz7scXut","spotify:track:0Nz23ikouHjjqmw6VDMXA6","spotify:track:0hN3gqhsyQryxyfUwbsAJY","spotify:track:25yA3k7cBNDqejRJUun4Qe","spotify:track:2oVHoIWuMqI5NVz6WYn7Hz","spotify:track:3Symf7eRIlddMJNXtbA6IK","spotify:track:5dvPoqBSwHiFR0uGBppPYQ","spotify:track:2PC92mpsc0XCCILU85Dlvz","spotify:track:3L5n8FHAe9RCsrKDSDbU0t","spotify:track:7nrVOGH5g2XbCcVIPc1z2v","spotify:track:4g8BvKyw10b20zfYS3LnoL","spotify:track:4WfGDkm99oLJSAtELYZYEd","spotify:track:4yagkb6nJCRcfjUhaOVHTw","spotify:track:7smWOsdOrLqq87a8sRN0PH"]},{"timestamp_utc":"2024-01-15T04:30:43.114Z","context_time":1705293043114,"message_context_uri":"spotify:playlist:37i9dQZEVXbkoSs7u90Cw1","message_is_made_for_user":true,"message_registration_country":"AE","message_track_uris":["spotify:track:387j61utwXNE7Bvi5UTR2k","spotify:track:4VDBbopB3UhOlcx75rkWwt","spotify:track:1iQ06QdWjaaPKmwQrJCx49","spotify:track:0ifLfKVPTV1vHjfI0JThNR","spotify:track:1Mk4uWL6Lm8J6nz4WQET91","spotify:track:5zUyrAi43jmbmbYTw3YfWH","spotify:track:1lwKbdVuFlou24SwMNzXS0","spotify:track:5aeXimPjlHeqI7W7hJIqlo","spotify:track:0kMpRZWiwAdum2eQejAxMN","spotify:track:3CMdlCNPXJZXouXZHKhYyV","spotify:track:1NMYbsFZyxwHRNaLGzFGWh","spotify:track:48H87I4tgT2V5n7ZDYXGPn","spotify:track:4rGk0zUXzCUcx5bpImm6Sz","spotify:track:1L76kNHnalqy4A0akwoFmK","spotify:track:1WdNlshDUsaL21mGhM9S4v","spotify:track:0iCnlo8Q8bK0494ymMiTde","spotify:track:4v5Aa7j4svuQTzNQQxC0RY","spotify:track:5lN6KXXwe3DGTbPZbmzQ50","spotify:track:7xoaG78ccu5r4tOdxNcgVR","spotify:track:65Dyv2vhfwrn1V4OiozCZS","spotify:track:2DaPCl392tphoi2TqslBdG","spotify:track:1iTuo6oMChhXAgu2LCFUiz","spotify:track:1UrEASMdC7chHBizGbpAyx","spotify:track:3CkKFRGxteb3TBCNmZy5LB","spotify:track:1SKFUmtqIz0oJbma9K5LWK","spotify:track:20z7Q3CO1gRP2Yb8UhIQdq","spotify:track:4eSrby5sF3zwEgE3mGXJYV","spotify:track:10jkTly01YHd0Jm2xUtFlB","spotify:track:1yxTbuOoym1Dx56OeTyQEB","spotify:track:0wvBwIlOv5Ze5jTB4EeBPg"]},{"timestamp_utc":"2023-11-28T02:44:49.881Z","context_time":1701139489881,"message_context_uri":"spotify:playlist:37i9dQZEVXbkoSs7u90Cw1","message_is_made_for_user":true,"message_registration_country":"AE","message_track_uris":["spotify:track:0a2NP8kiyBjKMKr9yBgmu9","spotify:track:6i3DBbjAzfZqbnqCND1hlX","spotify:track:04odGx95cXda5ykFx7Pj6w","spotify:track:7993rSSJhvymBDhq0WeDeE","spotify:track:38jz2nov1xFBOzsNE60u4a","spotify:track:6vzZxRUs3Zxg0HuLoqtt6c","spotify:track:207YcqxaFYsOdJarlqyjWl","spotify:track:23DBeqyrFvncQFf9jiuklR","spotify:track:1MiFS7YNfRcJCiI8y33RUe","spotify:track:1qSLt4bauTRIlLo0lw1U02","spotify:track:27xsLWmSmEAiXABnOngOw7","spotify:track:5oT4UO1LJMgnl26aIy88ox","spotify:track:44PrLucPgjbVvMAjpvMDCk","spotify:track:1eKQFMKfCezCI1LF2oByEm","spotify:track:47IzfVVQs2orvksB1CGRvO","spotify:track:25jISSHAd4q2CVTsO7EHJM","spotify:track:0gkQiwGIuneO08yaQ68HK5","spotify:track:2jm0UrP5A9ccJ3twMI8cVq","spotify:track:4Q6S45dcKtAIBaGnGZ4yD6","spotify:track:1B8g9FFMUDXlCpjJfiiT9D","spotify:track:4pAd9xohEcZ1NzQD3S14pP","spotify:track:4U5RcowtVHV0S9QqfxKPs7","spotify:track:7FJ5LdspkWcxPUkV8dzMOL","spotify:track:5dRD4iHgRS4yKWCh2pdqUV","spotify:track:322TvI9HYg7Tz2DizOAniw","spotify:track:2pgMykS4vRfWjCn3HBW7Sl","spotify:track:1anIxQ7F0J7Ayc9QMNwkNB","spotify:track:3duI7TT4kzLtoqf4PeUR3Z","spotify:track:7JJOUjiewemzvDXbq0LcBY","spotify:track:51h7YmJJp0FSM6AyFycRJ2"]},{"timestamp_utc":"2023-11-12T17:21:55.355Z","context_time":1699809715355,"message_context_uri":"spotify:playlist:37i9dQZEVXbkoSs7u90Cw1","message_is_made_for_user":true,"message_registration_country":"AE","message_track_uris":["spotify:track:65kga6DUIuueiZHR52tWcb","spotify:track:0Rs8QF1GrAar2X4pHRutmL","spotify:track:1anIxQ7F0J7Ayc9QMNwkNB","spotify:track:2pgMykS4vRfWjCn3HBW7Sl","spotify:track:2m4s3761CzsYyH5lYoF4qu","spotify:track:2FOzVtoTjalPbQpsvAVTTI","spotify:track:6qkwieeAuu97CLLtuooHd3","spotify:track:3n3TDfjL4RD8sC8ZOakgkW","spotify:track:6bpQvYciF8jtaaXrGV6AKp","spotify:track:6vPFDbyzSYWAL7r3Waa7BZ","spotify:track:3yHyiUDJdz02FZ6jfUbsmY","spotify:track:35ugbjNCcL0d39D1C5eyt4","spotify:track:18NWRHrL2xqGIw5SGSyf3S","spotify:track:6vB3eJU3ZOZXJxOKRcT2kl","spotify:track:3DNluh1hzpBIwIhMNAhN3V","spotify:track:1sZFDDmmBVkcHOpV6AB0Nx","spotify:track:5PlvEOKEO40fwk1qHXGuH0","spotify:track:6FahmzZYKH0zb2f9hrVsvw","spotify:track:2tb3BSK1Z9s5n7YynbuAbp","spotify:track:6SfLZ94X4nImZChgqmoP3q","spotify:track:1REh5aFdSnrw06A67wpGk3","spotify:track:0i7hmzHYai87aZzlKT7MhO","spotify:track:6p8DwAh6wJ7S6jmpyYlBYp","spotify:track:4cbN08AlbNtanvMNhPVcPe","spotify:track:0nXYmY9YtiHkFGlR3cusur","spotify:track:72vuBPMhwFNlSYpTSf6fVD","spotify:track:7eQBzDRjBJ2bCkRKxNPbXm","spotify:track:0VBdCcaY6ERYKF7fZXQ8YX","spotify:track:4EWPO9rKRv0orDRlYLnn4J","spotify:track:3gJFL7cF0ziqTjqcIMNqv3"]},{"timestamp_utc":"2023-11-21T16:07:02.887Z","context_time":1700582822887,"message_context_uri":"spotify:playlist:37i9dQZEVXbkoSs7u90Cw1","message_is_made_for_user":true,"message_registration_country":"AE","message_track_uris":["spotify:track:1qSLt4bauTRIlLo0lw1U02","spotify:track:27xsLWmSmEAiXABnOngOw7","spotify:track:5oT4UO1LJMgnl26aIy88ox","spotify:track:1eKQFMKfCezCI1LF2oByEm","spotify:track:47IzfVVQs2orvksB1CGRvO","spotify:track:0gkQiwGIuneO08yaQ68HK5","spotify:track:0jqki4UKTXtSkyZjKiTUsi","spotify:track:4Q6S45dcKtAIBaGnGZ4yD6","spotify:track:3ZzUOWnQuNxenx2MbZqtYq","spotify:track:7q8RDjLprHOErgwz4ReQGA","spotify:track:50ISJbc0MNUxfzrhDg2k92","spotify:track:4m2af7wCfOyYLBQZ3l7xLs","spotify:track:0e9puAKZblpFaZyEZ0ZcJ6","spotify:track:322TvI9HYg7Tz2DizOAniw","spotify:track:2pgMykS4vRfWjCn3HBW7Sl","spotify:track:2m4s3761CzsYyH5lYoF4qu","spotify:track:1anIxQ7F0J7Ayc9QMNwkNB","spotify:track:0zboMHaQqZSc5g094rpR9j","spotify:track:5St1eVg5tOIK9HEmMJznLX","spotify:track:0Qo75eJMY72e5IQJt0Dz9z","spotify:track:2aj9isuH4NcbdNKJrOWMTs","spotify:track:0Q37Ax4ON1mIANcQvqfbOl","spotify:track:6qkwieeAuu97CLLtuooHd3","spotify:track:7JJOUjiewemzvDXbq0LcBY","spotify:track:51h7YmJJp0FSM6AyFycRJ2","spotify:track:6bpQvYciF8jtaaXrGV6AKp","spotify:track:3n3TDfjL4RD8sC8ZOakgkW","spotify:track:4bWN06wez00SFofUjnvLfG","spotify:track:72DQsnQrsEwfgTgaqRzahu","spotify:track:3DNluh1hzpBIwIhMNAhN3V"]},{"timestamp_utc":"2023-11-15T03:36:28.203Z","context_time":1700019388203,"message_context_uri":"spotify:playlist:37i9dQZEVXbkoSs7u90Cw1","message_is_made_for_user":true,"message_registration_country":"AE","message_track_uris":["spotify:track:1eKQFMKfCezCI1LF2oByEm","spotify:track:0e9puAKZblpFaZyEZ0ZcJ6","spotify:track:322TvI9HYg7Tz2DizOAniw","spotify:track:65kga6DUIuueiZHR52tWcb","spotify:track:1anIxQ7F0J7Ayc9QMNwkNB","spotify:track:2pgMykS4vRfWjCn3HBW7Sl","spotify:track:2m4s3761CzsYyH5lYoF4qu","spotify:track:6qkwieeAuu97CLLtuooHd3","spotify:track:3n3TDfjL4RD8sC8ZOakgkW","spotify:track:6bpQvYciF8jtaaXrGV6AKp","spotify:track:3yHyiUDJdz02FZ6jfUbsmY","spotify:track:6vPFDbyzSYWAL7r3Waa7BZ","spotify:track:35ugbjNCcL0d39D1C5eyt4","spotify:track:18NWRHrL2xqGIw5SGSyf3S","spotify:track:6vB3eJU3ZOZXJxOKRcT2kl","spotify:track:3DNluh1hzpBIwIhMNAhN3V","spotify:track:5PlvEOKEO40fwk1qHXGuH0","spotify:track:1sZFDDmmBVkcHOpV6AB0Nx","spotify:track:6FahmzZYKH0zb2f9hrVsvw","spotify:track:2tb3BSK1Z9s5n7YynbuAbp","spotify:track:6SfLZ94X4nImZChgqmoP3q","spotify:track:0i7hmzHYai87aZzlKT7MhO","spotify:track:0nXYmY9YtiHkFGlR3cusur","spotify:track:4cbN08AlbNtanvMNhPVcPe","spotify:track:6p8DwAh6wJ7S6jmpyYlBYp","spotify:track:1REh5aFdSnrw06A67wpGk3","spotify:track:72vuBPMhwFNlSYpTSf6fVD","spotify:track:7eQBzDRjBJ2bCkRKxNPbXm","spotify:track:3gJFL7cF0ziqTjqcIMNqv3","spotify:track:6sQNYW4YycsO1c8uhZpdA2"]},{"timestamp_utc":"2023-11-14T14:39:33.491Z","context_time":1699972773491,"message_context_uri":"spotify:playlist:37i9dQZEVXbkoSs7u90Cw1","message_is_made_for_user":true,"message_registration_country":"AE","message_track_uris":["spotify:track:1eKQFMKfCezCI1LF2oByEm","spotify:track:0e9puAKZblpFaZyEZ0ZcJ6","spotify:track:322TvI9HYg7Tz2DizOAniw","spotify:track:65kga6DUIuueiZHR52tWcb","spotify:track:1anIxQ7F0J7Ayc9QMNwkNB","spotify:track:2pgMykS4vRfWjCn3HBW7Sl","spotify:track:2m4s3761CzsYyH5lYoF4qu","spotify:track:6qkwieeAuu97CLLtuooHd3","spotify:track:3n3TDfjL4RD8sC8ZOakgkW","spotify:track:6bpQvYciF8jtaaXrGV6AKp","spotify:track:3yHyiUDJdz02FZ6jfUbsmY","spotify:track:6vPFDbyzSYWAL7r3Waa7BZ","spotify:track:35ugbjNCcL0d39D1C5eyt4","spotify:track:18NWRHrL2xqGIw5SGSyf3S","spotify:track:6vB3eJU3ZOZXJxOKRcT2kl","spotify:track:3DNluh1hzpBIwIhMNAhN3V","spotify:track:5PlvEOKEO40fwk1qHXGuH0","spotify:track:1sZFDDmmBVkcHOpV6AB0Nx","spotify:track:6FahmzZYKH0zb2f9hrVsvw","spotify:track:2tb3BSK1Z9s5n7YynbuAbp","spotify:track:6SfLZ94X4nImZChgqmoP3q","spotify:track:0i7hmzHYai87aZzlKT7MhO","spotify:track:0nXYmY9YtiHkFGlR3cusur","spotify:track:4cbN08AlbNtanvMNhPVcPe","spotify:track:6p8DwAh6wJ7S6jmpyYlBYp","spotify:track:1REh5aFdSnrw06A67wpGk3","spotify:track:72vuBPMhwFNlSYpTSf6fVD","spotify:track:7eQBzDRjBJ2bCkRKxNPbXm","spotify:track:3gJFL7cF0ziqTjqcIMNqv3","spotify:track:6sQNYW4YycsO1c8uhZpdA2"]},{"timestamp_utc":"2023-11-16T15:01:11.473Z","context_time":1700146871473,"message_context_uri":"spotify:playlist:37i9dQZEVXbkoSs7u90Cw1","message_is_made_for_user":true,"message_registration_country":"AE","message_track_uris":["spotify:track:1eKQFMKfCezCI1LF2oByEm","spotify:track:0e9puAKZblpFaZyEZ0ZcJ6","spotify:track:322TvI9HYg7Tz2DizOAniw","spotify:track:65kga6DUIuueiZHR52tWcb","spotify:track:1anIxQ7F0J7Ayc9QMNwkNB","spotify:track:2pgMykS4vRfWjCn3HBW7Sl","spotify:track:2m4s3761CzsYyH5lYoF4qu","spotify:track:6qkwieeAuu97CLLtuooHd3","spotify:track:3n3TDfjL4RD8sC8ZOakgkW","spotify:track:6bpQvYciF8jtaaXrGV6AKp","spotify:track:3yHyiUDJdz02FZ6jfUbsmY","spotify:track:6vPFDbyzSYWAL7r3Waa7BZ","spotify:track:35ugbjNCcL0d39D1C5eyt4","spotify:track:18NWRHrL2xqGIw5SGSyf3S","spotify:track:6vB3eJU3ZOZXJxOKRcT2kl","spotify:track:3DNluh1hzpBIwIhMNAhN3V","spotify:track:1sZFDDmmBVkcHOpV6AB0Nx","spotify:track:5PlvEOKEO40fwk1qHXGuH0","spotify:track:6FahmzZYKH0zb2f9hrVsvw","spotify:track:6SfLZ94X4nImZChgqmoP3q","spotify:track:2tb3BSK1Z9s5n7YynbuAbp","spotify:track:0i7hmzHYai87aZzlKT7MhO","spotify:track:6p8DwAh6wJ7S6jmpyYlBYp","spotify:track:4cbN08AlbNtanvMNhPVcPe","spotify:track:0nXYmY9YtiHkFGlR3cusur","spotify:track:72vuBPMhwFNlSYpTSf6fVD","spotify:track:1REh5aFdSnrw06A67wpGk3","spotify:track:7eQBzDRjBJ2bCkRKxNPbXm","spotify:track:3gJFL7cF0ziqTjqcIMNqv3","spotify:track:6sQNYW4YycsO1c8uhZpdA2"]},{"timestamp_utc":"2023-12-16T19:32:38.464Z","context_time":1702755158464,"message_context_uri":"spotify:playlist:37i9dQZEVXbkoSs7u90Cw1","message_is_made_for_user":true,"message_registration_country":"AE","message_track_uris":["spotify:track:0Nz23ikouHjjqmw6VDMXA6","spotify:track:25yA3k7cBNDqejRJUun4Qe","spotify:track:74vhTmkzSXbNRlVe3dvsEw","spotify:track:0hN3gqhsyQryxyfUwbsAJY","spotify:track:2oVHoIWuMqI5NVz6WYn7Hz","spotify:track:5B8VpcIC3EAI3wke3XQoRy","spotify:track:5dvPoqBSwHiFR0uGBppPYQ","spotify:track:2PC92mpsc0XCCILU85Dlvz","spotify:track:3L5n8FHAe9RCsrKDSDbU0t","spotify:track:7nrVOGH5g2XbCcVIPc1z2v","spotify:track:74qIx2lHqfMB8SnlborPoG","spotify:track:4WfGDkm99oLJSAtELYZYEd","spotify:track:3QX2xbfH8LDUaHIA5YQmtO","spotify:track:4g8BvKyw10b20zfYS3LnoL","spotify:track:0jaX10A3R9z6iMdVrq6Xiz","spotify:track:4yagkb6nJCRcfjUhaOVHTw","spotify:track:4SmmoqGZXCido1Tcddy5cI","spotify:track:7smWOsdOrLqq87a8sRN0PH","spotify:track:35FFqjqaPv1Fr9B1GtJdZO","spotify:track:5XMglV3BsTZyr97DC9yqIb","spotify:track:31VM3M27RYAbkLcx69pLsG","spotify:track:7eKrZvt4uORY0DLABy7gMY","spotify:track:1lvoAUC071648FyyvUjKLO","spotify:track:7lEQxb3JnTJcj2bHrP6kwH","spotify:track:4lYXywil8gd4a5shYzcJjP","spotify:track:1YzzGuqqfI71YEdNYPYIhO","spotify:track:7993rSSJhvymBDhq0WeDeE","spotify:track:38jz2nov1xFBOzsNE60u4a","spotify:track:6vzZxRUs3Zxg0HuLoqtt6c","spotify:track:04odGx95cXda5ykFx7Pj6w"]},{"timestamp_utc":"2024-01-09T04:11:11.620Z","context_time":1704773471620,"message_context_uri":"spotify:playlist:37i9dQZEVXbkoSs7u90Cw1","message_is_made_for_user":true,"message_registration_country":"AE","message_track_uris":["spotify:track:0kMpRZWiwAdum2eQejAxMN","spotify:track:4qkUDUOPQyL4OPKkTpkpYj","spotify:track:1NMYbsFZyxwHRNaLGzFGWh","spotify:track:48H87I4tgT2V5n7ZDYXGPn","spotify:track:2DaPCl392tphoi2TqslBdG","spotify:track:1txUL9NNB7bbWYDLCaN4KV","spotify:track:1iTuo6oMChhXAgu2LCFUiz","spotify:track:6R417VYcuf4lNMg6dT1ueV","spotify:track:1UrEASMdC7chHBizGbpAyx","spotify:track:3lJOVcAw0GldtMbrZtuMeS","spotify:track:3CkKFRGxteb3TBCNmZy5LB","spotify:track:4eSrby5sF3zwEgE3mGXJYV","spotify:track:20z7Q3CO1gRP2Yb8UhIQdq","spotify:track:7EqH9On4VEdHFhiu5DdFzP","spotify:track:10jkTly01YHd0Jm2xUtFlB","spotify:track:1yxTbuOoym1Dx56OeTyQEB","spotify:track:0wvBwIlOv5Ze5jTB4EeBPg","spotify:track:3bE5E0AGPyHvmmA9LNoi5t","spotify:track:1b9VHDd6FJEzd7ecSHZj1S","spotify:track:64iqTKzDkiuhQ1JCjMUsBr","spotify:track:4aEv1igs7UqxBEHdicIcZV","spotify:track:0Ja4AAjauZDRquEz7scXut","spotify:track:1oAuFsdjYf9THTxwMHCIJO","spotify:track:0HMA7v4t7UaXonj9VmASAY","spotify:track:0Nz23ikouHjjqmw6VDMXA6","spotify:track:0hN3gqhsyQryxyfUwbsAJY","spotify:track:2oVHoIWuMqI5NVz6WYn7Hz","spotify:track:25yA3k7cBNDqejRJUun4Qe","spotify:track:1d3YFxKWh1Rx9y2sJJ9Jd2","spotify:track:2PC92mpsc0XCCILU85Dlvz"]},{"timestamp_utc":"2023-11-29T14:53:34.555Z","context_time":1701269614555,"message_context_uri":"spotify:playlist:37i9dQZEVXbkoSs7u90Cw1","message_is_made_for_user":true,"message_registration_country":"AE","message_track_uris":["spotify:track:0a2NP8kiyBjKMKr9yBgmu9","spotify:track:6i3DBbjAzfZqbnqCND1hlX","spotify:track:04odGx95cXda5ykFx7Pj6w","spotify:track:7993rSSJhvymBDhq0WeDeE","spotify:track:38jz2nov1xFBOzsNE60u4a","spotify:track:6vzZxRUs3Zxg0HuLoqtt6c","spotify:track:207YcqxaFYsOdJarlqyjWl","spotify:track:23DBeqyrFvncQFf9jiuklR","spotify:track:1MiFS7YNfRcJCiI8y33RUe","spotify:track:1qSLt4bauTRIlLo0lw1U02","spotify:track:27xsLWmSmEAiXABnOngOw7","spotify:track:5oT4UO1LJMgnl26aIy88ox","spotify:track:44PrLucPgjbVvMAjpvMDCk","spotify:track:1eKQFMKfCezCI1LF2oByEm","spotify:track:47IzfVVQs2orvksB1CGRvO","spotify:track:25jISSHAd4q2CVTsO7EHJM","spotify:track:0gkQiwGIuneO08yaQ68HK5","spotify:track:4U5RcowtVHV0S9QqfxKPs7","spotify:track:2jm0UrP5A9ccJ3twMI8cVq","spotify:track:4Q6S45dcKtAIBaGnGZ4yD6","spotify:track:5dRD4iHgRS4yKWCh2pdqUV","spotify:track:3HnpI9mWSRtOdHBrJxuUlD","spotify:track:1B8g9FFMUDXlCpjJfiiT9D","spotify:track:7FJ5LdspkWcxPUkV8dzMOL","spotify:track:322TvI9HYg7Tz2DizOAniw","spotify:track:2pgMykS4vRfWjCn3HBW7Sl","spotify:track:1anIxQ7F0J7Ayc9QMNwkNB","spotify:track:3duI7TT4kzLtoqf4PeUR3Z","spotify:track:7JJOUjiewemzvDXbq0LcBY","spotify:track:51h7YmJJp0FSM6AyFycRJ2"]},{"timestamp_utc":"2023-11-30T03:37:34.602Z","context_time":1701315454602,"message_context_uri":"spotify:playlist:37i9dQZEVXbkoSs7u90Cw1","message_is_made_for_user":true,"message_registration_country":"AE","message_track_uris":["spotify:track:0a2NP8kiyBjKMKr9yBgmu9","spotify:track:6i3DBbjAzfZqbnqCND1hlX","spotify:track:04odGx95cXda5ykFx7Pj6w","spotify:track:7993rSSJhvymBDhq0WeDeE","spotify:track:38jz2nov1xFBOzsNE60u4a","spotify:track:6vzZxRUs3Zxg0HuLoqtt6c","spotify:track:207YcqxaFYsOdJarlqyjWl","spotify:track:23DBeqyrFvncQFf9jiuklR","spotify:track:1MiFS7YNfRcJCiI8y33RUe","spotify:track:1qSLt4bauTRIlLo0lw1U02","spotify:track:27xsLWmSmEAiXABnOngOw7","spotify:track:5oT4UO1LJMgnl26aIy88ox","spotify:track:44PrLucPgjbVvMAjpvMDCk","spotify:track:1eKQFMKfCezCI1LF2oByEm","spotify:track:47IzfVVQs2orvksB1CGRvO","spotify:track:25jISSHAd4q2CVTsO7EHJM","spotify:track:0gkQiwGIuneO08yaQ68HK5","spotify:track:4U5RcowtVHV0S9QqfxKPs7","spotify:track:2jm0UrP5A9ccJ3twMI8cVq","spotify:track:4Q6S45dcKtAIBaGnGZ4yD6","spotify:track:5dRD4iHgRS4yKWCh2pdqUV","spotify:track:3HnpI9mWSRtOdHBrJxuUlD","spotify:track:1B8g9FFMUDXlCpjJfiiT9D","spotify:track:7FJ5LdspkWcxPUkV8dzMOL","spotify:track:322TvI9HYg7Tz2DizOAniw","spotify:track:2pgMykS4vRfWjCn3HBW7Sl","spotify:track:1anIxQ7F0J7Ayc9QMNwkNB","spotify:track:3duI7TT4kzLtoqf4PeUR3Z","spotify:track:7JJOUjiewemzvDXbq0LcBY","spotify:track:51h7YmJJp0FSM6AyFycRJ2"]},{"timestamp_utc":"2024-01-02T12:32:00.408Z","context_time":1704198720408,"message_context_uri":"spotify:playlist:37i9dQZEVXbkoSs7u90Cw1","message_is_made_for_user":true,"message_registration_country":"AE","message_track_uris":["spotify:track:2DaPCl392tphoi2TqslBdG","spotify:track:1txUL9NNB7bbWYDLCaN4KV","spotify:track:1iTuo6oMChhXAgu2LCFUiz","spotify:track:6R417VYcuf4lNMg6dT1ueV","spotify:track:1UrEASMdC7chHBizGbpAyx","spotify:track:6oRkOFfxvJ9KMopWbtd4D8","spotify:track:4eSrby5sF3zwEgE3mGXJYV","spotify:track:6M1B4hA3YNbMgkugKErPxV","spotify:track:7EqH9On4VEdHFhiu5DdFzP","spotify:track:3iFYJMrRS0fLrwDNVbqNF0","spotify:track:77B8mI3PW8x2ke5UIyevDl","spotify:track:10jkTly01YHd0Jm2xUtFlB","spotify:track:1yxTbuOoym1Dx56OeTyQEB","spotify:track:0wvBwIlOv5Ze5jTB4EeBPg","spotify:track:1b9VHDd6FJEzd7ecSHZj1S","spotify:track:6dwS1tgnir4zmbgburrUsA","spotify:track:0Ja4AAjauZDRquEz7scXut","spotify:track:0Nz23ikouHjjqmw6VDMXA6","spotify:track:0hN3gqhsyQryxyfUwbsAJY","spotify:track:25yA3k7cBNDqejRJUun4Qe","spotify:track:2oVHoIWuMqI5NVz6WYn7Hz","spotify:track:3Symf7eRIlddMJNXtbA6IK","spotify:track:5dvPoqBSwHiFR0uGBppPYQ","spotify:track:2PC92mpsc0XCCILU85Dlvz","spotify:track:3L5n8FHAe9RCsrKDSDbU0t","spotify:track:7nrVOGH5g2XbCcVIPc1z2v","spotify:track:4g8BvKyw10b20zfYS3LnoL","spotify:track:4WfGDkm99oLJSAtELYZYEd","spotify:track:4yagkb6nJCRcfjUhaOVHTw","spotify:track:7smWOsdOrLqq87a8sRN0PH"]},{"timestamp_utc":"2023-11-13T10:07:29.317Z","context_time":1699870049317,"message_context_uri":"spotify:playlist:37i9dQZEVXbkoSs7u90Cw1","message_is_made_for_user":true,"message_registration_country":"AE","message_track_uris":["spotify:track:65kga6DUIuueiZHR52tWcb","spotify:track:0Rs8QF1GrAar2X4pHRutmL","spotify:track:1anIxQ7F0J7Ayc9QMNwkNB","spotify:track:2pgMykS4vRfWjCn3HBW7Sl","spotify:track:2m4s3761CzsYyH5lYoF4qu","spotify:track:2FOzVtoTjalPbQpsvAVTTI","spotify:track:6qkwieeAuu97CLLtuooHd3","spotify:track:3n3TDfjL4RD8sC8ZOakgkW","spotify:track:6bpQvYciF8jtaaXrGV6AKp","spotify:track:6vPFDbyzSYWAL7r3Waa7BZ","spotify:track:3yHyiUDJdz02FZ6jfUbsmY","spotify:track:35ugbjNCcL0d39D1C5eyt4","spotify:track:18NWRHrL2xqGIw5SGSyf3S","spotify:track:6vB3eJU3ZOZXJxOKRcT2kl","spotify:track:3DNluh1hzpBIwIhMNAhN3V","spotify:track:1sZFDDmmBVkcHOpV6AB0Nx","spotify:track:6FahmzZYKH0zb2f9hrVsvw","spotify:track:5PlvEOKEO40fwk1qHXGuH0","spotify:track:2tb3BSK1Z9s5n7YynbuAbp","spotify:track:6SfLZ94X4nImZChgqmoP3q","spotify:track:0i7hmzHYai87aZzlKT7MhO","spotify:track:1REh5aFdSnrw06A67wpGk3","spotify:track:6p8DwAh6wJ7S6jmpyYlBYp","spotify:track:4cbN08AlbNtanvMNhPVcPe","spotify:track:0nXYmY9YtiHkFGlR3cusur","spotify:track:72vuBPMhwFNlSYpTSf6fVD","spotify:track:7eQBzDRjBJ2bCkRKxNPbXm","spotify:track:0VBdCcaY6ERYKF7fZXQ8YX","spotify:track:4EWPO9rKRv0orDRlYLnn4J","spotify:track:3gJFL7cF0ziqTjqcIMNqv3"]},{"timestamp_utc":"2023-12-03T15:34:09.251Z","context_time":1701617649251,"message_context_uri":"spotify:playlist:37i9dQZEVXbkoSs7u90Cw1","message_is_made_for_user":true,"message_registration_country":"AE","message_track_uris":["spotify:track:7DTTBTO7kv7iqcOH3S9lC4","spotify:track:7eKrZvt4uORY0DLABy7gMY","spotify:track:1lvoAUC071648FyyvUjKLO","spotify:track:0TL0LFcwIBF5eX7arDIKxY","spotify:track:7lEQxb3JnTJcj2bHrP6kwH","spotify:track:4lYXywil8gd4a5shYzcJjP","spotify:track:1YzzGuqqfI71YEdNYPYIhO","spotify:track:4ApCig0GTR4IEp7Ijsyo3r","spotify:track:5lPlIrWYNLUwEJCSsI6hFi","spotify:track:0YxKKO272sacGBJKjf6FnB","spotify:track:0a2NP8kiyBjKMKr9yBgmu9","spotify:track:04odGx95cXda5ykFx7Pj6w","spotify:track:2WyStEQoQLEYH21xnCx1Th","spotify:track:7993rSSJhvymBDhq0WeDeE","spotify:track:38jz2nov1xFBOzsNE60u4a","spotify:track:6vzZxRUs3Zxg0HuLoqtt6c","spotify:track:207YcqxaFYsOdJarlqyjWl","spotify:track:23DBeqyrFvncQFf9jiuklR","spotify:track:40Ynf67EqlVgyu9tF4aNxE","spotify:track:7FmrM318GcKjV0qHIuAGci","spotify:track:4IDtPcFhlaarYWzn9H8Be5","spotify:track:3ejqftsE4bgYpjXWp3sfhO","spotify:track:1qSLt4bauTRIlLo0lw1U02","spotify:track:5oT4UO1LJMgnl26aIy88ox","spotify:track:44PrLucPgjbVvMAjpvMDCk","spotify:track:47IzfVVQs2orvksB1CGRvO","spotify:track:1eKQFMKfCezCI1LF2oByEm","spotify:track:0gkQiwGIuneO08yaQ68HK5","spotify:track:322TvI9HYg7Tz2DizOAniw","spotify:track:3duI7TT4kzLtoqf4PeUR3Z"]},{"timestamp_utc":"2024-01-03T15:26:31.926Z","context_time":1704295591926,"message_context_uri":"spotify:playlist:37i9dQZEVXbkoSs7u90Cw1","message_is_made_for_user":true,"message_registration_country":"AE","message_track_uris":["spotify:track:2DaPCl392tphoi2TqslBdG","spotify:track:1txUL9NNB7bbWYDLCaN4KV","spotify:track:1iTuo6oMChhXAgu2LCFUiz","spotify:track:6R417VYcuf4lNMg6dT1ueV","spotify:track:1UrEASMdC7chHBizGbpAyx","spotify:track:6oRkOFfxvJ9KMopWbtd4D8","spotify:track:4eSrby5sF3zwEgE3mGXJYV","spotify:track:6M1B4hA3YNbMgkugKErPxV","spotify:track:7EqH9On4VEdHFhiu5DdFzP","spotify:track:3iFYJMrRS0fLrwDNVbqNF0","spotify:track:77B8mI3PW8x2ke5UIyevDl","spotify:track:10jkTly01YHd0Jm2xUtFlB","spotify:track:1yxTbuOoym1Dx56OeTyQEB","spotify:track:0wvBwIlOv5Ze5jTB4EeBPg","spotify:track:1b9VHDd6FJEzd7ecSHZj1S","spotify:track:6dwS1tgnir4zmbgburrUsA","spotify:track:0Ja4AAjauZDRquEz7scXut","spotify:track:0Nz23ikouHjjqmw6VDMXA6","spotify:track:0hN3gqhsyQryxyfUwbsAJY","spotify:track:25yA3k7cBNDqejRJUun4Qe","spotify:track:2oVHoIWuMqI5NVz6WYn7Hz","spotify:track:3Symf7eRIlddMJNXtbA6IK","spotify:track:5dvPoqBSwHiFR0uGBppPYQ","spotify:track:2PC92mpsc0XCCILU85Dlvz","spotify:track:3L5n8FHAe9RCsrKDSDbU0t","spotify:track:7nrVOGH5g2XbCcVIPc1z2v","spotify:track:4g8BvKyw10b20zfYS3LnoL","spotify:track:4WfGDkm99oLJSAtELYZYEd","spotify:track:4yagkb6nJCRcfjUhaOVHTw","spotify:track:7smWOsdOrLqq87a8sRN0PH"]},{"timestamp_utc":"2023-12-06T18:52:14.072Z","context_time":1701888734072,"message_context_uri":"spotify:playlist:37i9dQZEVXbkoSs7u90Cw1","message_is_made_for_user":true,"message_registration_country":"AE","message_track_uris":["spotify:track:7DTTBTO7kv7iqcOH3S9lC4","spotify:track:7eKrZvt4uORY0DLABy7gMY","spotify:track:1lvoAUC071648FyyvUjKLO","spotify:track:0TL0LFcwIBF5eX7arDIKxY","spotify:track:7lEQxb3JnTJcj2bHrP6kwH","spotify:track:4lYXywil8gd4a5shYzcJjP","spotify:track:1YzzGuqqfI71YEdNYPYIhO","spotify:track:4ApCig0GTR4IEp7Ijsyo3r","spotify:track:0YxKKO272sacGBJKjf6FnB","spotify:track:5lPlIrWYNLUwEJCSsI6hFi","spotify:track:0a2NP8kiyBjKMKr9yBgmu9","spotify:track:04odGx95cXda5ykFx7Pj6w","spotify:track:2WyStEQoQLEYH21xnCx1Th","spotify:track:7993rSSJhvymBDhq0WeDeE","spotify:track:38jz2nov1xFBOzsNE60u4a","spotify:track:6vzZxRUs3Zxg0HuLoqtt6c","spotify:track:207YcqxaFYsOdJarlqyjWl","spotify:track:23DBeqyrFvncQFf9jiuklR","spotify:track:4IDtPcFhlaarYWzn9H8Be5","spotify:track:40Ynf67EqlVgyu9tF4aNxE","spotify:track:7FmrM318GcKjV0qHIuAGci","spotify:track:3ejqftsE4bgYpjXWp3sfhO","spotify:track:1qSLt4bauTRIlLo0lw1U02","spotify:track:5oT4UO1LJMgnl26aIy88ox","spotify:track:44PrLucPgjbVvMAjpvMDCk","spotify:track:47IzfVVQs2orvksB1CGRvO","spotify:track:1eKQFMKfCezCI1LF2oByEm","spotify:track:0gkQiwGIuneO08yaQ68HK5","spotify:track:322TvI9HYg7Tz2DizOAniw","spotify:track:3duI7TT4kzLtoqf4PeUR3Z"]},{"timestamp_utc":"2024-02-06T05:28:38.834Z","context_time":1707197318834,"message_context_uri":"spotify:playlist:37i9dQZEVXbkoSs7u90Cw1","message_is_made_for_user":true,"message_registration_country":"AE","message_track_uris":["spotify:track:6PNhbEHabSERm2YHXOSizH","spotify:track:4m47o25mr9RqvOUzfRyjy3","spotify:track:2PCkD2ZI7zf0LOWdH2gNz5","spotify:track:5Msv4zzbXHxK0TzlAySK1J","spotify:track:5t36KLDvhjsIaat1DDxrDo","spotify:track:2usXJTfTSRH5ajx7uLnBfQ","spotify:track:2edUKbpj6GxgViPiL5EbIq","spotify:track:1QBMPnuR6v9OB1VVxgJB5G","spotify:track:1aooH2O4Y2neJ1aIZZOAml","spotify:track:047lJsrqwXM73t5a1iSF2B","spotify:track:6BfILljHPy6KB2W8Yp0Dr0","spotify:track:5eB2NeY2Px3EgzIsizedZe","spotify:track:3UxSyVzUrRxG3VyNNWWt7u","spotify:track:3wysCwuzcaaPGEibqnU3nz","spotify:track:2mtCcdlsA2q4CNzVWxlyxi","spotify:track:6F9zM0nqQE9OOsMGIPEQMD","spotify:track:6fMZ7g4JvGCRgLldIxi6Sl","spotify:track:753yGdIWiuZUn1cDRJziT7","spotify:track:6RaNwx66fRVaj07kZZWwV5","spotify:track:2IzKfxGPk9hbJdGJhZWIAb","spotify:track:5gPRX0AmXth8OKLJ0QuKae","spotify:track:7qn2DjVZipJEJ5h0p1HvSL","spotify:track:493n4dFutqZNQugLgPuQ1p","spotify:track:48TbjAwxnglZJzeEj7r3jv","spotify:track:0U8xGuKNtRz2PWVGaLjJ8V","spotify:track:4smqvcyz6mp27zNIUnLuvV","spotify:track:7lzPCtx5j2JRFhbsGpbzQ7","spotify:track:38uKHamvGkT14HDIGo5cOv","spotify:track:3EJslhR33350RLGMb6eOAg","spotify:track:387j61utwXNE7Bvi5UTR2k"]},{"timestamp_utc":"2023-11-10T03:02:49.766Z","context_time":1699585369766,"message_context_uri":"spotify:playlist:37i9dQZEVXbkoSs7u90Cw1","message_is_made_for_user":true,"message_registration_country":"AE","message_track_uris":["spotify:track:65kga6DUIuueiZHR52tWcb","spotify:track:0Rs8QF1GrAar2X4pHRutmL","spotify:track:1anIxQ7F0J7Ayc9QMNwkNB","spotify:track:2pgMykS4vRfWjCn3HBW7Sl","spotify:track:2m4s3761CzsYyH5lYoF4qu","spotify:track:58AHOShrLAeG4FXnt9pSvV","spotify:track:11L6UdbFQFoNVW7gsDvIBY","spotify:track:2FOzVtoTjalPbQpsvAVTTI","spotify:track:1mlAyS24nG7NZu50fR0sQP","spotify:track:6qkwieeAuu97CLLtuooHd3","spotify:track:3n3TDfjL4RD8sC8ZOakgkW","spotify:track:6bpQvYciF8jtaaXrGV6AKp","spotify:track:3yHyiUDJdz02FZ6jfUbsmY","spotify:track:6vPFDbyzSYWAL7r3Waa7BZ","spotify:track:35ugbjNCcL0d39D1C5eyt4","spotify:track:18NWRHrL2xqGIw5SGSyf3S","spotify:track:6vB3eJU3ZOZXJxOKRcT2kl","spotify:track:3DNluh1hzpBIwIhMNAhN3V","spotify:track:1sZFDDmmBVkcHOpV6AB0Nx","spotify:track:6FahmzZYKH0zb2f9hrVsvw","spotify:track:5PlvEOKEO40fwk1qHXGuH0","spotify:track:6SfLZ94X4nImZChgqmoP3q","spotify:track:7iUnVwZuLdZcIKdYN6cnq6","spotify:track:6p8DwAh6wJ7S6jmpyYlBYp","spotify:track:1REh5aFdSnrw06A67wpGk3","spotify:track:0i7hmzHYai87aZzlKT7MhO","spotify:track:66v97IvccVkHt40FIOq1LH","spotify:track:0VBdCcaY6ERYKF7fZXQ8YX","spotify:track:4EWPO9rKRv0orDRlYLnn4J","spotify:track:3gJFL7cF0ziqTjqcIMNqv3"]},{"timestamp_utc":"2023-11-11T10:13:40.460Z","context_time":1699697620460,"message_context_uri":"spotify:playlist:37i9dQZEVXbkoSs7u90Cw1","message_is_made_for_user":true,"message_registration_country":"AE","message_track_uris":["spotify:track:65kga6DUIuueiZHR52tWcb","spotify:track:0Rs8QF1GrAar2X4pHRutmL","spotify:track:1anIxQ7F0J7Ayc9QMNwkNB","spotify:track:2pgMykS4vRfWjCn3HBW7Sl","spotify:track:2m4s3761CzsYyH5lYoF4qu","spotify:track:2FOzVtoTjalPbQpsvAVTTI","spotify:track:6qkwieeAuu97CLLtuooHd3","spotify:track:3n3TDfjL4RD8sC8ZOakgkW","spotify:track:6bpQvYciF8jtaaXrGV6AKp","spotify:track:6vPFDbyzSYWAL7r3Waa7BZ","spotify:track:3yHyiUDJdz02FZ6jfUbsmY","spotify:track:35ugbjNCcL0d39D1C5eyt4","spotify:track:18NWRHrL2xqGIw5SGSyf3S","spotify:track:6vB3eJU3ZOZXJxOKRcT2kl","spotify:track:3DNluh1hzpBIwIhMNAhN3V","spotify:track:6FahmzZYKH0zb2f9hrVsvw","spotify:track:1sZFDDmmBVkcHOpV6AB0Nx","spotify:track:5PlvEOKEO40fwk1qHXGuH0","spotify:track:1REh5aFdSnrw06A67wpGk3","spotify:track:2tb3BSK1Z9s5n7YynbuAbp","spotify:track:4cbN08AlbNtanvMNhPVcPe","spotify:track:6SfLZ94X4nImZChgqmoP3q","spotify:track:6p8DwAh6wJ7S6jmpyYlBYp","spotify:track:0nXYmY9YtiHkFGlR3cusur","spotify:track:0i7hmzHYai87aZzlKT7MhO","spotify:track:7eQBzDRjBJ2bCkRKxNPbXm","spotify:track:72vuBPMhwFNlSYpTSf6fVD","spotify:track:0VBdCcaY6ERYKF7fZXQ8YX","spotify:track:4EWPO9rKRv0orDRlYLnn4J","spotify:track:3gJFL7cF0ziqTjqcIMNqv3"]},{"timestamp_utc":"2023-12-08T03:03:25.419Z","context_time":1702004605419,"message_context_uri":"spotify:playlist:37i9dQZEVXbkoSs7u90Cw1","message_is_made_for_user":true,"message_registration_country":"AE","message_track_uris":["spotify:track:3L5n8FHAe9RCsrKDSDbU0t","spotify:track:7nrVOGH5g2XbCcVIPc1z2v","spotify:track:3bWm8ejTzkMhPSdBnpxLvl","spotify:track:3QX2xbfH8LDUaHIA5YQmtO","spotify:track:4g8BvKyw10b20zfYS3LnoL","spotify:track:0jaX10A3R9z6iMdVrq6Xiz","spotify:track:4yagkb6nJCRcfjUhaOVHTw","spotify:track:4SmmoqGZXCido1Tcddy5cI","spotify:track:7smWOsdOrLqq87a8sRN0PH","spotify:track:1Ma9rGhZMloUx9NEpTNYpF","spotify:track:7DTTBTO7kv7iqcOH3S9lC4","spotify:track:7eKrZvt4uORY0DLABy7gMY","spotify:track:1lvoAUC071648FyyvUjKLO","spotify:track:7lEQxb3JnTJcj2bHrP6kwH","spotify:track:4lYXywil8gd4a5shYzcJjP","spotify:track:1YzzGuqqfI71YEdNYPYIhO","spotify:track:0TL0LFcwIBF5eX7arDIKxY","spotify:track:0YxKKO272sacGBJKjf6FnB","spotify:track:4BGGZZnhsaQTxdnDxwzLSu","spotify:track:0a2NP8kiyBjKMKr9yBgmu9","spotify:track:7993rSSJhvymBDhq0WeDeE","spotify:track:38jz2nov1xFBOzsNE60u4a","spotify:track:6vzZxRUs3Zxg0HuLoqtt6c","spotify:track:04odGx95cXda5ykFx7Pj6w","spotify:track:1qSLt4bauTRIlLo0lw1U02","spotify:track:5oT4UO1LJMgnl26aIy88ox","spotify:track:44PrLucPgjbVvMAjpvMDCk","spotify:track:1eKQFMKfCezCI1LF2oByEm","spotify:track:322TvI9HYg7Tz2DizOAniw","spotify:track:3duI7TT4kzLtoqf4PeUR3Z"]},{"timestamp_utc":"2023-11-15T12:02:40.487Z","context_time":1700049760487,"message_context_uri":"spotify:playlist:37i9dQZEVXbkoSs7u90Cw1","message_is_made_for_user":true,"message_registration_country":"AE","message_track_uris":["spotify:track:1eKQFMKfCezCI1LF2oByEm","spotify:track:0e9puAKZblpFaZyEZ0ZcJ6","spotify:track:322TvI9HYg7Tz2DizOAniw","spotify:track:65kga6DUIuueiZHR52tWcb","spotify:track:1anIxQ7F0J7Ayc9QMNwkNB","spotify:track:2pgMykS4vRfWjCn3HBW7Sl","spotify:track:2m4s3761CzsYyH5lYoF4qu","spotify:track:6qkwieeAuu97CLLtuooHd3","spotify:track:3n3TDfjL4RD8sC8ZOakgkW","spotify:track:6bpQvYciF8jtaaXrGV6AKp","spotify:track:3yHyiUDJdz02FZ6jfUbsmY","spotify:track:6vPFDbyzSYWAL7r3Waa7BZ","spotify:track:35ugbjNCcL0d39D1C5eyt4","spotify:track:18NWRHrL2xqGIw5SGSyf3S","spotify:track:6vB3eJU3ZOZXJxOKRcT2kl","spotify:track:3DNluh1hzpBIwIhMNAhN3V","spotify:track:1sZFDDmmBVkcHOpV6AB0Nx","spotify:track:5PlvEOKEO40fwk1qHXGuH0","spotify:track:6FahmzZYKH0zb2f9hrVsvw","spotify:track:6SfLZ94X4nImZChgqmoP3q","spotify:track:2tb3BSK1Z9s5n7YynbuAbp","spotify:track:0i7hmzHYai87aZzlKT7MhO","spotify:track:6p8DwAh6wJ7S6jmpyYlBYp","spotify:track:4cbN08AlbNtanvMNhPVcPe","spotify:track:0nXYmY9YtiHkFGlR3cusur","spotify:track:72vuBPMhwFNlSYpTSf6fVD","spotify:track:1REh5aFdSnrw06A67wpGk3","spotify:track:7eQBzDRjBJ2bCkRKxNPbXm","spotify:track:3gJFL7cF0ziqTjqcIMNqv3","spotify:track:6sQNYW4YycsO1c8uhZpdA2"]},{"timestamp_utc":"2023-12-15T20:43:05.714Z","context_time":1702672985714,"message_context_uri":"spotify:playlist:37i9dQZEVXbkoSs7u90Cw1","message_is_made_for_user":true,"message_registration_country":"AE","message_track_uris":["spotify:track:0Nz23ikouHjjqmw6VDMXA6","spotify:track:25yA3k7cBNDqejRJUun4Qe","spotify:track:74vhTmkzSXbNRlVe3dvsEw","spotify:track:0hN3gqhsyQryxyfUwbsAJY","spotify:track:2oVHoIWuMqI5NVz6WYn7Hz","spotify:track:5B8VpcIC3EAI3wke3XQoRy","spotify:track:5dvPoqBSwHiFR0uGBppPYQ","spotify:track:2PC92mpsc0XCCILU85Dlvz","spotify:track:3L5n8FHAe9RCsrKDSDbU0t","spotify:track:7nrVOGH5g2XbCcVIPc1z2v","spotify:track:74qIx2lHqfMB8SnlborPoG","spotify:track:3bWm8ejTzkMhPSdBnpxLvl","spotify:track:3QX2xbfH8LDUaHIA5YQmtO","spotify:track:4g8BvKyw10b20zfYS3LnoL","spotify:track:0jaX10A3R9z6iMdVrq6Xiz","spotify:track:4yagkb6nJCRcfjUhaOVHTw","spotify:track:4SmmoqGZXCido1Tcddy5cI","spotify:track:7smWOsdOrLqq87a8sRN0PH","spotify:track:7eKrZvt4uORY0DLABy7gMY","spotify:track:1lvoAUC071648FyyvUjKLO","spotify:track:7lEQxb3JnTJcj2bHrP6kwH","spotify:track:4lYXywil8gd4a5shYzcJjP","spotify:track:1YzzGuqqfI71YEdNYPYIhO","spotify:track:0a2NP8kiyBjKMKr9yBgmu9","spotify:track:7993rSSJhvymBDhq0WeDeE","spotify:track:38jz2nov1xFBOzsNE60u4a","spotify:track:6vzZxRUs3Zxg0HuLoqtt6c","spotify:track:04odGx95cXda5ykFx7Pj6w","spotify:track:1qSLt4bauTRIlLo0lw1U02","spotify:track:44PrLucPgjbVvMAjpvMDCk"]},{"timestamp_utc":"2023-12-12T06:19:17.713Z","context_time":1702361957713,"message_context_uri":"spotify:playlist:37i9dQZEVXbkoSs7u90Cw1","message_is_made_for_user":true,"message_registration_country":"AE","message_track_uris":["spotify:track:3L5n8FHAe9RCsrKDSDbU0t","spotify:track:7nrVOGH5g2XbCcVIPc1z2v","spotify:track:3bWm8ejTzkMhPSdBnpxLvl","spotify:track:3QX2xbfH8LDUaHIA5YQmtO","spotify:track:4g8BvKyw10b20zfYS3LnoL","spotify:track:0jaX10A3R9z6iMdVrq6Xiz","spotify:track:4yagkb6nJCRcfjUhaOVHTw","spotify:track:4SmmoqGZXCido1Tcddy5cI","spotify:track:40WxJ4Hfbv5LQccPpLvaWJ","spotify:track:7smWOsdOrLqq87a8sRN0PH","spotify:track:76ieW8NzMzwmm7C6P9sVLJ","spotify:track:78vQAz3r7BzqbhsLjwvuC7","spotify:track:7eKrZvt4uORY0DLABy7gMY","spotify:track:1lvoAUC071648FyyvUjKLO","spotify:track:7lEQxb3JnTJcj2bHrP6kwH","spotify:track:4lYXywil8gd4a5shYzcJjP","spotify:track:1YzzGuqqfI71YEdNYPYIhO","spotify:track:7GHRy23VSudw3apSiBV5IF","spotify:track:0u9gJXogkZQ7oLaOWHO7OU","spotify:track:2wmGV5OnYd0Bv1pwbSzMYq","spotify:track:7yDHHVKLbvDmVw1XXhDDIO","spotify:track:0TL0LFcwIBF5eX7arDIKxY","spotify:track:0a2NP8kiyBjKMKr9yBgmu9","spotify:track:6i3DBbjAzfZqbnqCND1hlX","spotify:track:7993rSSJhvymBDhq0WeDeE","spotify:track:38jz2nov1xFBOzsNE60u4a","spotify:track:6vzZxRUs3Zxg0HuLoqtt6c","spotify:track:04odGx95cXda5ykFx7Pj6w","spotify:track:1qSLt4bauTRIlLo0lw1U02","spotify:track:44PrLucPgjbVvMAjpvMDCk"]},{"timestamp_utc":"2024-01-04T09:44:12.597Z","context_time":1704361452597,"message_context_uri":"spotify:playlist:37i9dQZEVXbkoSs7u90Cw1","message_is_made_for_user":true,"message_registration_country":"AE","message_track_uris":["spotify:track:2DaPCl392tphoi2TqslBdG","spotify:track:1txUL9NNB7bbWYDLCaN4KV","spotify:track:1iTuo6oMChhXAgu2LCFUiz","spotify:track:6R417VYcuf4lNMg6dT1ueV","spotify:track:1UrEASMdC7chHBizGbpAyx","spotify:track:6oRkOFfxvJ9KMopWbtd4D8","spotify:track:4eSrby5sF3zwEgE3mGXJYV","spotify:track:6M1B4hA3YNbMgkugKErPxV","spotify:track:7EqH9On4VEdHFhiu5DdFzP","spotify:track:3iFYJMrRS0fLrwDNVbqNF0","spotify:track:77B8mI3PW8x2ke5UIyevDl","spotify:track:10jkTly01YHd0Jm2xUtFlB","spotify:track:1yxTbuOoym1Dx56OeTyQEB","spotify:track:0wvBwIlOv5Ze5jTB4EeBPg","spotify:track:1b9VHDd6FJEzd7ecSHZj1S","spotify:track:6dwS1tgnir4zmbgburrUsA","spotify:track:0Ja4AAjauZDRquEz7scXut","spotify:track:0Nz23ikouHjjqmw6VDMXA6","spotify:track:0hN3gqhsyQryxyfUwbsAJY","spotify:track:25yA3k7cBNDqejRJUun4Qe","spotify:track:2oVHoIWuMqI5NVz6WYn7Hz","spotify:track:3Symf7eRIlddMJNXtbA6IK","spotify:track:5dvPoqBSwHiFR0uGBppPYQ","spotify:track:2PC92mpsc0XCCILU85Dlvz","spotify:track:3L5n8FHAe9RCsrKDSDbU0t","spotify:track:7nrVOGH5g2XbCcVIPc1z2v","spotify:track:4g8BvKyw10b20zfYS3LnoL","spotify:track:4WfGDkm99oLJSAtELYZYEd","spotify:track:4yagkb6nJCRcfjUhaOVHTw","spotify:track:7smWOsdOrLqq87a8sRN0PH"]},{"timestamp_utc":"2023-11-14T14:39:33.460Z","context_time":1699972773460,"message_context_uri":"spotify:playlist:37i9dQZEVXbkoSs7u90Cw1","message_is_made_for_user":true,"message_registration_country":"AE","message_track_uris":["spotify:track:1eKQFMKfCezCI1LF2oByEm","spotify:track:0e9puAKZblpFaZyEZ0ZcJ6","spotify:track:322TvI9HYg7Tz2DizOAniw","spotify:track:65kga6DUIuueiZHR52tWcb","spotify:track:1anIxQ7F0J7Ayc9QMNwkNB","spotify:track:2pgMykS4vRfWjCn3HBW7Sl","spotify:track:2m4s3761CzsYyH5lYoF4qu","spotify:track:6qkwieeAuu97CLLtuooHd3","spotify:track:3n3TDfjL4RD8sC8ZOakgkW","spotify:track:6bpQvYciF8jtaaXrGV6AKp","spotify:track:3yHyiUDJdz02FZ6jfUbsmY","spotify:track:6vPFDbyzSYWAL7r3Waa7BZ","spotify:track:35ugbjNCcL0d39D1C5eyt4","spotify:track:18NWRHrL2xqGIw5SGSyf3S","spotify:track:6vB3eJU3ZOZXJxOKRcT2kl","spotify:track:3DNluh1hzpBIwIhMNAhN3V","spotify:track:5PlvEOKEO40fwk1qHXGuH0","spotify:track:1sZFDDmmBVkcHOpV6AB0Nx","spotify:track:6FahmzZYKH0zb2f9hrVsvw","spotify:track:2tb3BSK1Z9s5n7YynbuAbp","spotify:track:6SfLZ94X4nImZChgqmoP3q","spotify:track:0i7hmzHYai87aZzlKT7MhO","spotify:track:0nXYmY9YtiHkFGlR3cusur","spotify:track:4cbN08AlbNtanvMNhPVcPe","spotify:track:6p8DwAh6wJ7S6jmpyYlBYp","spotify:track:1REh5aFdSnrw06A67wpGk3","spotify:track:72vuBPMhwFNlSYpTSf6fVD","spotify:track:7eQBzDRjBJ2bCkRKxNPbXm","spotify:track:3gJFL7cF0ziqTjqcIMNqv3","spotify:track:6sQNYW4YycsO1c8uhZpdA2"]},{"timestamp_utc":"2024-01-04T09:44:12.597Z","context_time":1704361452597,"message_context_uri":"spotify:playlist:37i9dQZEVXbkoSs7u90Cw1","message_is_made_for_user":true,"message_registration_country":"AE","message_track_uris":["spotify:track:2DaPCl392tphoi2TqslBdG","spotify:track:1txUL9NNB7bbWYDLCaN4KV","spotify:track:1iTuo6oMChhXAgu2LCFUiz","spotify:track:6R417VYcuf4lNMg6dT1ueV","spotify:track:1UrEASMdC7chHBizGbpAyx","spotify:track:6oRkOFfxvJ9KMopWbtd4D8","spotify:track:4eSrby5sF3zwEgE3mGXJYV","spotify:track:6M1B4hA3YNbMgkugKErPxV","spotify:track:7EqH9On4VEdHFhiu5DdFzP","spotify:track:3iFYJMrRS0fLrwDNVbqNF0","spotify:track:77B8mI3PW8x2ke5UIyevDl","spotify:track:10jkTly01YHd0Jm2xUtFlB","spotify:track:1yxTbuOoym1Dx56OeTyQEB","spotify:track:0wvBwIlOv5Ze5jTB4EeBPg","spotify:track:1b9VHDd6FJEzd7ecSHZj1S","spotify:track:6dwS1tgnir4zmbgburrUsA","spotify:track:0Ja4AAjauZDRquEz7scXut","spotify:track:0Nz23ikouHjjqmw6VDMXA6","spotify:track:0hN3gqhsyQryxyfUwbsAJY","spotify:track:25yA3k7cBNDqejRJUun4Qe","spotify:track:2oVHoIWuMqI5NVz6WYn7Hz","spotify:track:3Symf7eRIlddMJNXtbA6IK","spotify:track:5dvPoqBSwHiFR0uGBppPYQ","spotify:track:2PC92mpsc0XCCILU85Dlvz","spotify:track:3L5n8FHAe9RCsrKDSDbU0t","spotify:track:7nrVOGH5g2XbCcVIPc1z2v","spotify:track:4g8BvKyw10b20zfYS3LnoL","spotify:track:4WfGDkm99oLJSAtELYZYEd","spotify:track:4yagkb6nJCRcfjUhaOVHTw","spotify:track:7smWOsdOrLqq87a8sRN0PH"]},{"timestamp_utc":"2024-01-31T17:59:15.614Z","context_time":1706723955614,"message_context_uri":"spotify:playlist:37i9dQZEVXbkoSs7u90Cw1","message_is_made_for_user":true,"message_registration_country":"AE","message_track_uris":["spotify:track:1QBMPnuR6v9OB1VVxgJB5G","spotify:track:1aooH2O4Y2neJ1aIZZOAml","spotify:track:047lJsrqwXM73t5a1iSF2B","spotify:track:0M0ANKNzmM4Odd7FNKghzW","spotify:track:6BfILljHPy6KB2W8Yp0Dr0","spotify:track:5eB2NeY2Px3EgzIsizedZe","spotify:track:3UxSyVzUrRxG3VyNNWWt7u","spotify:track:3wysCwuzcaaPGEibqnU3nz","spotify:track:2mtCcdlsA2q4CNzVWxlyxi","spotify:track:6F9zM0nqQE9OOsMGIPEQMD","spotify:track:6fMZ7g4JvGCRgLldIxi6Sl","spotify:track:5hzeUW4M10HRnSJyoQrH9x","spotify:track:7qn2DjVZipJEJ5h0p1HvSL","spotify:track:493n4dFutqZNQugLgPuQ1p","spotify:track:48TbjAwxnglZJzeEj7r3jv","spotify:track:7D6LiMiacu0gA5r299CxSp","spotify:track:0U8xGuKNtRz2PWVGaLjJ8V","spotify:track:4smqvcyz6mp27zNIUnLuvV","spotify:track:7lzPCtx5j2JRFhbsGpbzQ7","spotify:track:38uKHamvGkT14HDIGo5cOv","spotify:track:3EJslhR33350RLGMb6eOAg","spotify:track:1iB69nxVl29xhgqPQybrfY","spotify:track:2fIlZvbVnLBP5Q5nm4d1IN","spotify:track:0UldiKdMIMpWBxexAiEEen","spotify:track:4hOwZ6d11H6AKI5odjKTub","spotify:track:7zp98Ss6AfbryqI95507du","spotify:track:6BrZBHB0bQlCPJNZuuaqqu","spotify:track:49F2PdDfcTrVjACRPlsviv","spotify:track:2GsMrIHrRAkasLyhx3B4xN","spotify:track:387j61utwXNE7Bvi5UTR2k"]},{"timestamp_utc":"2024-02-05T04:31:51.135Z","context_time":1707107511135,"message_context_uri":"spotify:playlist:37i9dQZEVXbkoSs7u90Cw1","message_is_made_for_user":true,"message_registration_country":"AE","message_track_uris":["spotify:track:6PNhbEHabSERm2YHXOSizH","spotify:track:4m47o25mr9RqvOUzfRyjy3","spotify:track:2PCkD2ZI7zf0LOWdH2gNz5","spotify:track:5Msv4zzbXHxK0TzlAySK1J","spotify:track:5t36KLDvhjsIaat1DDxrDo","spotify:track:2usXJTfTSRH5ajx7uLnBfQ","spotify:track:2edUKbpj6GxgViPiL5EbIq","spotify:track:1QBMPnuR6v9OB1VVxgJB5G","spotify:track:1aooH2O4Y2neJ1aIZZOAml","spotify:track:047lJsrqwXM73t5a1iSF2B","spotify:track:6BfILljHPy6KB2W8Yp0Dr0","spotify:track:5eB2NeY2Px3EgzIsizedZe","spotify:track:3UxSyVzUrRxG3VyNNWWt7u","spotify:track:3wysCwuzcaaPGEibqnU3nz","spotify:track:2mtCcdlsA2q4CNzVWxlyxi","spotify:track:6F9zM0nqQE9OOsMGIPEQMD","spotify:track:6fMZ7g4JvGCRgLldIxi6Sl","spotify:track:753yGdIWiuZUn1cDRJziT7","spotify:track:6RaNwx66fRVaj07kZZWwV5","spotify:track:2IzKfxGPk9hbJdGJhZWIAb","spotify:track:5gPRX0AmXth8OKLJ0QuKae","spotify:track:7qn2DjVZipJEJ5h0p1HvSL","spotify:track:493n4dFutqZNQugLgPuQ1p","spotify:track:48TbjAwxnglZJzeEj7r3jv","spotify:track:0U8xGuKNtRz2PWVGaLjJ8V","spotify:track:4smqvcyz6mp27zNIUnLuvV","spotify:track:7lzPCtx5j2JRFhbsGpbzQ7","spotify:track:38uKHamvGkT14HDIGo5cOv","spotify:track:3EJslhR33350RLGMb6eOAg","spotify:track:387j61utwXNE7Bvi5UTR2k"]},{"timestamp_utc":"2023-12-09T20:17:59.838Z","context_time":1702153079838,"message_context_uri":"spotify:playlist:37i9dQZEVXbkoSs7u90Cw1","message_is_made_for_user":true,"message_registration_country":"AE","message_track_uris":["spotify:track:3L5n8FHAe9RCsrKDSDbU0t","spotify:track:7nrVOGH5g2XbCcVIPc1z2v","spotify:track:3bWm8ejTzkMhPSdBnpxLvl","spotify:track:3QX2xbfH8LDUaHIA5YQmtO","spotify:track:4g8BvKyw10b20zfYS3LnoL","spotify:track:0jaX10A3R9z6iMdVrq6Xiz","spotify:track:4yagkb6nJCRcfjUhaOVHTw","spotify:track:4SmmoqGZXCido1Tcddy5cI","spotify:track:40WxJ4Hfbv5LQccPpLvaWJ","spotify:track:7smWOsdOrLqq87a8sRN0PH","spotify:track:76ieW8NzMzwmm7C6P9sVLJ","spotify:track:78vQAz3r7BzqbhsLjwvuC7","spotify:track:7eKrZvt4uORY0DLABy7gMY","spotify:track:1lvoAUC071648FyyvUjKLO","spotify:track:7lEQxb3JnTJcj2bHrP6kwH","spotify:track:4lYXywil8gd4a5shYzcJjP","spotify:track:1YzzGuqqfI71YEdNYPYIhO","spotify:track:0TL0LFcwIBF5eX7arDIKxY","spotify:track:2wmGV5OnYd0Bv1pwbSzMYq","spotify:track:7GHRy23VSudw3apSiBV5IF","spotify:track:4BGGZZnhsaQTxdnDxwzLSu","spotify:track:0u9gJXogkZQ7oLaOWHO7OU","spotify:track:0a2NP8kiyBjKMKr9yBgmu9","spotify:track:6i3DBbjAzfZqbnqCND1hlX","spotify:track:7993rSSJhvymBDhq0WeDeE","spotify:track:38jz2nov1xFBOzsNE60u4a","spotify:track:6vzZxRUs3Zxg0HuLoqtt6c","spotify:track:04odGx95cXda5ykFx7Pj6w","spotify:track:1qSLt4bauTRIlLo0lw1U02","spotify:track:44PrLucPgjbVvMAjpvMDCk"]},{"timestamp_utc":"2023-11-23T04:05:25.571Z","context_time":1700712325571,"message_context_uri":"spotify:playlist:37i9dQZEVXbkoSs7u90Cw1","message_is_made_for_user":true,"message_registration_country":"AE","message_track_uris":["spotify:track:1qSLt4bauTRIlLo0lw1U02","spotify:track:27xsLWmSmEAiXABnOngOw7","spotify:track:5oT4UO1LJMgnl26aIy88ox","spotify:track:1eKQFMKfCezCI1LF2oByEm","spotify:track:47IzfVVQs2orvksB1CGRvO","spotify:track:0gkQiwGIuneO08yaQ68HK5","spotify:track:0jqki4UKTXtSkyZjKiTUsi","spotify:track:4Q6S45dcKtAIBaGnGZ4yD6","spotify:track:3ZzUOWnQuNxenx2MbZqtYq","spotify:track:7q8RDjLprHOErgwz4ReQGA","spotify:track:50ISJbc0MNUxfzrhDg2k92","spotify:track:4m2af7wCfOyYLBQZ3l7xLs","spotify:track:0e9puAKZblpFaZyEZ0ZcJ6","spotify:track:322TvI9HYg7Tz2DizOAniw","spotify:track:2pgMykS4vRfWjCn3HBW7Sl","spotify:track:2m4s3761CzsYyH5lYoF4qu","spotify:track:1anIxQ7F0J7Ayc9QMNwkNB","spotify:track:0zboMHaQqZSc5g094rpR9j","spotify:track:5St1eVg5tOIK9HEmMJznLX","spotify:track:0Qo75eJMY72e5IQJt0Dz9z","spotify:track:2aj9isuH4NcbdNKJrOWMTs","spotify:track:0Q37Ax4ON1mIANcQvqfbOl","spotify:track:6qkwieeAuu97CLLtuooHd3","spotify:track:7JJOUjiewemzvDXbq0LcBY","spotify:track:51h7YmJJp0FSM6AyFycRJ2","spotify:track:6bpQvYciF8jtaaXrGV6AKp","spotify:track:3n3TDfjL4RD8sC8ZOakgkW","spotify:track:4bWN06wez00SFofUjnvLfG","spotify:track:72DQsnQrsEwfgTgaqRzahu","spotify:track:3DNluh1hzpBIwIhMNAhN3V"]},{"timestamp_utc":"2023-12-04T07:51:08.546Z","context_time":1701676268546,"message_context_uri":"spotify:playlist:37i9dQZEVXbkoSs7u90Cw1","message_is_made_for_user":true,"message_registration_country":"AE","message_track_uris":["spotify:track:7DTTBTO7kv7iqcOH3S9lC4","spotify:track:7eKrZvt4uORY0DLABy7gMY","spotify:track:1lvoAUC071648FyyvUjKLO","spotify:track:0TL0LFcwIBF5eX7arDIKxY","spotify:track:7lEQxb3JnTJcj2bHrP6kwH","spotify:track:4lYXywil8gd4a5shYzcJjP","spotify:track:1YzzGuqqfI71YEdNYPYIhO","spotify:track:4ApCig0GTR4IEp7Ijsyo3r","spotify:track:5lPlIrWYNLUwEJCSsI6hFi","spotify:track:0YxKKO272sacGBJKjf6FnB","spotify:track:0a2NP8kiyBjKMKr9yBgmu9","spotify:track:04odGx95cXda5ykFx7Pj6w","spotify:track:2WyStEQoQLEYH21xnCx1Th","spotify:track:7993rSSJhvymBDhq0WeDeE","spotify:track:38jz2nov1xFBOzsNE60u4a","spotify:track:6vzZxRUs3Zxg0HuLoqtt6c","spotify:track:207YcqxaFYsOdJarlqyjWl","spotify:track:23DBeqyrFvncQFf9jiuklR","spotify:track:40Ynf67EqlVgyu9tF4aNxE","spotify:track:7FmrM318GcKjV0qHIuAGci","spotify:track:4IDtPcFhlaarYWzn9H8Be5","spotify:track:3ejqftsE4bgYpjXWp3sfhO","spotify:track:1qSLt4bauTRIlLo0lw1U02","spotify:track:5oT4UO1LJMgnl26aIy88ox","spotify:track:44PrLucPgjbVvMAjpvMDCk","spotify:track:47IzfVVQs2orvksB1CGRvO","spotify:track:1eKQFMKfCezCI1LF2oByEm","spotify:track:0gkQiwGIuneO08yaQ68HK5","spotify:track:322TvI9HYg7Tz2DizOAniw","spotify:track:3duI7TT4kzLtoqf4PeUR3Z"]},{"timestamp_utc":"2023-12-14T04:38:17.038Z","context_time":1702528697038,"message_context_uri":"spotify:playlist:37i9dQZEVXbkoSs7u90Cw1","message_is_made_for_user":true,"message_registration_country":"AE","message_track_uris":["spotify:track:3L5n8FHAe9RCsrKDSDbU0t","spotify:track:7nrVOGH5g2XbCcVIPc1z2v","spotify:track:74qIx2lHqfMB8SnlborPoG","spotify:track:3bWm8ejTzkMhPSdBnpxLvl","spotify:track:3QX2xbfH8LDUaHIA5YQmtO","spotify:track:4g8BvKyw10b20zfYS3LnoL","spotify:track:0jaX10A3R9z6iMdVrq6Xiz","spotify:track:4yagkb6nJCRcfjUhaOVHTw","spotify:track:4SmmoqGZXCido1Tcddy5cI","spotify:track:40WxJ4Hfbv5LQccPpLvaWJ","spotify:track:7smWOsdOrLqq87a8sRN0PH","spotify:track:76ieW8NzMzwmm7C6P9sVLJ","spotify:track:78vQAz3r7BzqbhsLjwvuC7","spotify:track:7eKrZvt4uORY0DLABy7gMY","spotify:track:1lvoAUC071648FyyvUjKLO","spotify:track:7lEQxb3JnTJcj2bHrP6kwH","spotify:track:4lYXywil8gd4a5shYzcJjP","spotify:track:1YzzGuqqfI71YEdNYPYIhO","spotify:track:7GHRy23VSudw3apSiBV5IF","spotify:track:0u9gJXogkZQ7oLaOWHO7OU","spotify:track:2wmGV5OnYd0Bv1pwbSzMYq","spotify:track:0TL0LFcwIBF5eX7arDIKxY","spotify:track:0a2NP8kiyBjKMKr9yBgmu9","spotify:track:6i3DBbjAzfZqbnqCND1hlX","spotify:track:7993rSSJhvymBDhq0WeDeE","spotify:track:38jz2nov1xFBOzsNE60u4a","spotify:track:6vzZxRUs3Zxg0HuLoqtt6c","spotify:track:04odGx95cXda5ykFx7Pj6w","spotify:track:1qSLt4bauTRIlLo0lw1U02","spotify:track:44PrLucPgjbVvMAjpvMDCk"]},{"timestamp_utc":"2023-12-04T07:51:08.555Z","context_time":1701676268555,"message_context_uri":"spotify:playlist:37i9dQZEVXbkoSs7u90Cw1","message_is_made_for_user":true,"message_registration_country":"AE","message_track_uris":["spotify:track:7DTTBTO7kv7iqcOH3S9lC4","spotify:track:7eKrZvt4uORY0DLABy7gMY","spotify:track:1lvoAUC071648FyyvUjKLO","spotify:track:0TL0LFcwIBF5eX7arDIKxY","spotify:track:7lEQxb3JnTJcj2bHrP6kwH","spotify:track:4lYXywil8gd4a5shYzcJjP","spotify:track:1YzzGuqqfI71YEdNYPYIhO","spotify:track:4ApCig0GTR4IEp7Ijsyo3r","spotify:track:5lPlIrWYNLUwEJCSsI6hFi","spotify:track:0YxKKO272sacGBJKjf6FnB","spotify:track:0a2NP8kiyBjKMKr9yBgmu9","spotify:track:04odGx95cXda5ykFx7Pj6w","spotify:track:2WyStEQoQLEYH21xnCx1Th","spotify:track:7993rSSJhvymBDhq0WeDeE","spotify:track:38jz2nov1xFBOzsNE60u4a","spotify:track:6vzZxRUs3Zxg0HuLoqtt6c","spotify:track:207YcqxaFYsOdJarlqyjWl","spotify:track:23DBeqyrFvncQFf9jiuklR","spotify:track:40Ynf67EqlVgyu9tF4aNxE","spotify:track:7FmrM318GcKjV0qHIuAGci","spotify:track:4IDtPcFhlaarYWzn9H8Be5","spotify:track:3ejqftsE4bgYpjXWp3sfhO","spotify:track:1qSLt4bauTRIlLo0lw1U02","spotify:track:5oT4UO1LJMgnl26aIy88ox","spotify:track:44PrLucPgjbVvMAjpvMDCk","spotify:track:47IzfVVQs2orvksB1CGRvO","spotify:track:1eKQFMKfCezCI1LF2oByEm","spotify:track:0gkQiwGIuneO08yaQ68HK5","spotify:track:322TvI9HYg7Tz2DizOAniw","spotify:track:3duI7TT4kzLtoqf4PeUR3Z"]},{"timestamp_utc":"2023-12-13T13:07:44.317Z","context_time":1702472864317,"message_context_uri":"spotify:playlist:37i9dQZEVXbkoSs7u90Cw1","message_is_made_for_user":true,"message_registration_country":"AE","message_track_uris":["spotify:track:3L5n8FHAe9RCsrKDSDbU0t","spotify:track:7nrVOGH5g2XbCcVIPc1z2v","spotify:track:74qIx2lHqfMB8SnlborPoG","spotify:track:3bWm8ejTzkMhPSdBnpxLvl","spotify:track:3QX2xbfH8LDUaHIA5YQmtO","spotify:track:4g8BvKyw10b20zfYS3LnoL","spotify:track:0jaX10A3R9z6iMdVrq6Xiz","spotify:track:4yagkb6nJCRcfjUhaOVHTw","spotify:track:4SmmoqGZXCido1Tcddy5cI","spotify:track:40WxJ4Hfbv5LQccPpLvaWJ","spotify:track:7smWOsdOrLqq87a8sRN0PH","spotify:track:76ieW8NzMzwmm7C6P9sVLJ","spotify:track:78vQAz3r7BzqbhsLjwvuC7","spotify:track:7eKrZvt4uORY0DLABy7gMY","spotify:track:1lvoAUC071648FyyvUjKLO","spotify:track:7lEQxb3JnTJcj2bHrP6kwH","spotify:track:4lYXywil8gd4a5shYzcJjP","spotify:track:1YzzGuqqfI71YEdNYPYIhO","spotify:track:7GHRy23VSudw3apSiBV5IF","spotify:track:0u9gJXogkZQ7oLaOWHO7OU","spotify:track:2wmGV5OnYd0Bv1pwbSzMYq","spotify:track:0TL0LFcwIBF5eX7arDIKxY","spotify:track:0a2NP8kiyBjKMKr9yBgmu9","spotify:track:6i3DBbjAzfZqbnqCND1hlX","spotify:track:7993rSSJhvymBDhq0WeDeE","spotify:track:38jz2nov1xFBOzsNE60u4a","spotify:track:6vzZxRUs3Zxg0HuLoqtt6c","spotify:track:04odGx95cXda5ykFx7Pj6w","spotify:track:1qSLt4bauTRIlLo0lw1U02","spotify:track:44PrLucPgjbVvMAjpvMDCk"]},{"timestamp_utc":"2024-01-05T09:42:22.190Z","context_time":1704447742190,"message_context_uri":"spotify:playlist:37i9dQZEVXbkoSs7u90Cw1","message_is_made_for_user":true,"message_registration_country":"AE","message_track_uris":["spotify:track:4eOsLkHjhbcMRry9pOfePU","spotify:track:0kMpRZWiwAdum2eQejAxMN","spotify:track:1NMYbsFZyxwHRNaLGzFGWh","spotify:track:48H87I4tgT2V5n7ZDYXGPn","spotify:track:2DaPCl392tphoi2TqslBdG","spotify:track:1iTuo6oMChhXAgu2LCFUiz","spotify:track:6R417VYcuf4lNMg6dT1ueV","spotify:track:1UrEASMdC7chHBizGbpAyx","spotify:track:3lJOVcAw0GldtMbrZtuMeS","spotify:track:4eSrby5sF3zwEgE3mGXJYV","spotify:track:20z7Q3CO1gRP2Yb8UhIQdq","spotify:track:6M1B4hA3YNbMgkugKErPxV","spotify:track:4ZeBqKuLKts0jv1ke3JfIY","spotify:track:7EqH9On4VEdHFhiu5DdFzP","spotify:track:10jkTly01YHd0Jm2xUtFlB","spotify:track:1yxTbuOoym1Dx56OeTyQEB","spotify:track:0wvBwIlOv5Ze5jTB4EeBPg","spotify:track:0Nz23ikouHjjqmw6VDMXA6","spotify:track:0hN3gqhsyQryxyfUwbsAJY","spotify:track:2oVHoIWuMqI5NVz6WYn7Hz","spotify:track:3Symf7eRIlddMJNXtbA6IK","spotify:track:25yA3k7cBNDqejRJUun4Qe","spotify:track:5dvPoqBSwHiFR0uGBppPYQ","spotify:track:2PC92mpsc0XCCILU85Dlvz","spotify:track:3L5n8FHAe9RCsrKDSDbU0t","spotify:track:7nrVOGH5g2XbCcVIPc1z2v","spotify:track:4g8BvKyw10b20zfYS3LnoL","spotify:track:4yagkb6nJCRcfjUhaOVHTw","spotify:track:4WfGDkm99oLJSAtELYZYEd","spotify:track:7smWOsdOrLqq87a8sRN0PH"]},{"timestamp_utc":"2023-12-25T07:53:05.552Z","context_time":1703490785552,"message_context_uri":"spotify:playlist:37i9dQZEVXbkoSs7u90Cw1","message_is_made_for_user":true,"message_registration_country":"AE","message_track_uris":["spotify:track:7EqH9On4VEdHFhiu5DdFzP","spotify:track:5Lvwzaf8BTuRDBmQ1GyeNA","spotify:track:3iFYJMrRS0fLrwDNVbqNF0","spotify:track:7kXRY7Tberw5S1iVLeYwmz","spotify:track:77B8mI3PW8x2ke5UIyevDl","spotify:track:1yxTbuOoym1Dx56OeTyQEB","spotify:track:0Ja4AAjauZDRquEz7scXut","spotify:track:0HMA7v4t7UaXonj9VmASAY","spotify:track:6oYQO84yM4ZrrOj9ssxDMl","spotify:track:0Nz23ikouHjjqmw6VDMXA6","spotify:track:0hN3gqhsyQryxyfUwbsAJY","spotify:track:25yA3k7cBNDqejRJUun4Qe","spotify:track:2oVHoIWuMqI5NVz6WYn7Hz","spotify:track:3Symf7eRIlddMJNXtbA6IK","spotify:track:5dvPoqBSwHiFR0uGBppPYQ","spotify:track:2PC92mpsc0XCCILU85Dlvz","spotify:track:3L5n8FHAe9RCsrKDSDbU0t","spotify:track:7nrVOGH5g2XbCcVIPc1z2v","spotify:track:74qIx2lHqfMB8SnlborPoG","spotify:track:4g8BvKyw10b20zfYS3LnoL","spotify:track:0jaX10A3R9z6iMdVrq6Xiz","spotify:track:3QX2xbfH8LDUaHIA5YQmtO","spotify:track:4WfGDkm99oLJSAtELYZYEd","spotify:track:4yagkb6nJCRcfjUhaOVHTw","spotify:track:4SmmoqGZXCido1Tcddy5cI","spotify:track:7smWOsdOrLqq87a8sRN0PH","spotify:track:7eKrZvt4uORY0DLABy7gMY","spotify:track:7lEQxb3JnTJcj2bHrP6kwH","spotify:track:1lvoAUC071648FyyvUjKLO","spotify:track:31VM3M27RYAbkLcx69pLsG"]},{"timestamp_utc":"2023-12-05T02:30:36.037Z","context_time":1701743436037,"message_context_uri":"spotify:playlist:37i9dQZEVXbkoSs7u90Cw1","message_is_made_for_user":true,"message_registration_country":"AE","message_track_uris":["spotify:track:7DTTBTO7kv7iqcOH3S9lC4","spotify:track:7eKrZvt4uORY0DLABy7gMY","spotify:track:1lvoAUC071648FyyvUjKLO","spotify:track:0TL0LFcwIBF5eX7arDIKxY","spotify:track:7lEQxb3JnTJcj2bHrP6kwH","spotify:track:4lYXywil8gd4a5shYzcJjP","spotify:track:1YzzGuqqfI71YEdNYPYIhO","spotify:track:4ApCig0GTR4IEp7Ijsyo3r","spotify:track:0YxKKO272sacGBJKjf6FnB","spotify:track:5lPlIrWYNLUwEJCSsI6hFi","spotify:track:0a2NP8kiyBjKMKr9yBgmu9","spotify:track:04odGx95cXda5ykFx7Pj6w","spotify:track:2WyStEQoQLEYH21xnCx1Th","spotify:track:7993rSSJhvymBDhq0WeDeE","spotify:track:38jz2nov1xFBOzsNE60u4a","spotify:track:6vzZxRUs3Zxg0HuLoqtt6c","spotify:track:207YcqxaFYsOdJarlqyjWl","spotify:track:23DBeqyrFvncQFf9jiuklR","spotify:track:40Ynf67EqlVgyu9tF4aNxE","spotify:track:7FmrM318GcKjV0qHIuAGci","spotify:track:4IDtPcFhlaarYWzn9H8Be5","spotify:track:3ejqftsE4bgYpjXWp3sfhO","spotify:track:1qSLt4bauTRIlLo0lw1U02","spotify:track:5oT4UO1LJMgnl26aIy88ox","spotify:track:44PrLucPgjbVvMAjpvMDCk","spotify:track:47IzfVVQs2orvksB1CGRvO","spotify:track:1eKQFMKfCezCI1LF2oByEm","spotify:track:0gkQiwGIuneO08yaQ68HK5","spotify:track:322TvI9HYg7Tz2DizOAniw","spotify:track:3duI7TT4kzLtoqf4PeUR3Z"]},{"timestamp_utc":"2024-01-26T11:40:03.098Z","context_time":1706269203098,"message_context_uri":"spotify:playlist:37i9dQZEVXbkoSs7u90Cw1","message_is_made_for_user":true,"message_registration_country":"AE","message_track_uris":["spotify:track:1QBMPnuR6v9OB1VVxgJB5G","spotify:track:1aooH2O4Y2neJ1aIZZOAml","spotify:track:047lJsrqwXM73t5a1iSF2B","spotify:track:0M0ANKNzmM4Odd7FNKghzW","spotify:track:6BfILljHPy6KB2W8Yp0Dr0","spotify:track:5eB2NeY2Px3EgzIsizedZe","spotify:track:3UxSyVzUrRxG3VyNNWWt7u","spotify:track:3wysCwuzcaaPGEibqnU3nz","spotify:track:2mtCcdlsA2q4CNzVWxlyxi","spotify:track:6F9zM0nqQE9OOsMGIPEQMD","spotify:track:7qn2DjVZipJEJ5h0p1HvSL","spotify:track:493n4dFutqZNQugLgPuQ1p","spotify:track:48TbjAwxnglZJzeEj7r3jv","spotify:track:7D6LiMiacu0gA5r299CxSp","spotify:track:0U8xGuKNtRz2PWVGaLjJ8V","spotify:track:4smqvcyz6mp27zNIUnLuvV","spotify:track:7lzPCtx5j2JRFhbsGpbzQ7","spotify:track:38uKHamvGkT14HDIGo5cOv","spotify:track:3EJslhR33350RLGMb6eOAg","spotify:track:1iB69nxVl29xhgqPQybrfY","spotify:track:2fIlZvbVnLBP5Q5nm4d1IN","spotify:track:0UldiKdMIMpWBxexAiEEen","spotify:track:4hOwZ6d11H6AKI5odjKTub","spotify:track:6T1ELgQrvY6AXv6fH5c5GH","spotify:track:1KtWLU6UP55Zs90OGWsGZB","spotify:track:6BrZBHB0bQlCPJNZuuaqqu","spotify:track:387j61utwXNE7Bvi5UTR2k","spotify:track:6EwyCau3GPq7Deyekzp8x5","spotify:track:1NMYbsFZyxwHRNaLGzFGWh","spotify:track:2DaPCl392tphoi2TqslBdG"]},{"timestamp_utc":"2023-11-14T02:32:43.639Z","context_time":1699929163639,"message_context_uri":"spotify:playlist:37i9dQZEVXbkoSs7u90Cw1","message_is_made_for_user":true,"message_registration_country":"AE","message_track_uris":["spotify:track:1eKQFMKfCezCI1LF2oByEm","spotify:track:0e9puAKZblpFaZyEZ0ZcJ6","spotify:track:322TvI9HYg7Tz2DizOAniw","spotify:track:65kga6DUIuueiZHR52tWcb","spotify:track:1anIxQ7F0J7Ayc9QMNwkNB","spotify:track:2pgMykS4vRfWjCn3HBW7Sl","spotify:track:2m4s3761CzsYyH5lYoF4qu","spotify:track:6qkwieeAuu97CLLtuooHd3","spotify:track:3n3TDfjL4RD8sC8ZOakgkW","spotify:track:6bpQvYciF8jtaaXrGV6AKp","spotify:track:6vPFDbyzSYWAL7r3Waa7BZ","spotify:track:3yHyiUDJdz02FZ6jfUbsmY","spotify:track:35ugbjNCcL0d39D1C5eyt4","spotify:track:18NWRHrL2xqGIw5SGSyf3S","spotify:track:6vB3eJU3ZOZXJxOKRcT2kl","spotify:track:3DNluh1hzpBIwIhMNAhN3V","spotify:track:1sZFDDmmBVkcHOpV6AB0Nx","spotify:track:5PlvEOKEO40fwk1qHXGuH0","spotify:track:6FahmzZYKH0zb2f9hrVsvw","spotify:track:2tb3BSK1Z9s5n7YynbuAbp","spotify:track:6SfLZ94X4nImZChgqmoP3q","spotify:track:0i7hmzHYai87aZzlKT7MhO","spotify:track:0nXYmY9YtiHkFGlR3cusur","spotify:track:6p8DwAh6wJ7S6jmpyYlBYp","spotify:track:1REh5aFdSnrw06A67wpGk3","spotify:track:4cbN08AlbNtanvMNhPVcPe","spotify:track:7eQBzDRjBJ2bCkRKxNPbXm","spotify:track:72vuBPMhwFNlSYpTSf6fVD","spotify:track:3gJFL7cF0ziqTjqcIMNqv3","spotify:track:6sQNYW4YycsO1c8uhZpdA2"]},{"timestamp_utc":"2023-11-13T13:46:40.596Z","context_time":1699883200596,"message_context_uri":"spotify:playlist:37i9dQZEVXbkoSs7u90Cw1","message_is_made_for_user":true,"message_registration_country":"AE","message_track_uris":["spotify:track:65kga6DUIuueiZHR52tWcb","spotify:track:0Rs8QF1GrAar2X4pHRutmL","spotify:track:1anIxQ7F0J7Ayc9QMNwkNB","spotify:track:2pgMykS4vRfWjCn3HBW7Sl","spotify:track:2m4s3761CzsYyH5lYoF4qu","spotify:track:2FOzVtoTjalPbQpsvAVTTI","spotify:track:6qkwieeAuu97CLLtuooHd3","spotify:track:3n3TDfjL4RD8sC8ZOakgkW","spotify:track:6bpQvYciF8jtaaXrGV6AKp","spotify:track:3yHyiUDJdz02FZ6jfUbsmY","spotify:track:6vPFDbyzSYWAL7r3Waa7BZ","spotify:track:35ugbjNCcL0d39D1C5eyt4","spotify:track:18NWRHrL2xqGIw5SGSyf3S","spotify:track:6vB3eJU3ZOZXJxOKRcT2kl","spotify:track:3DNluh1hzpBIwIhMNAhN3V","spotify:track:1sZFDDmmBVkcHOpV6AB0Nx","spotify:track:5PlvEOKEO40fwk1qHXGuH0","spotify:track:6FahmzZYKH0zb2f9hrVsvw","spotify:track:2tb3BSK1Z9s5n7YynbuAbp","spotify:track:6SfLZ94X4nImZChgqmoP3q","spotify:track:0i7hmzHYai87aZzlKT7MhO","spotify:track:6p8DwAh6wJ7S6jmpyYlBYp","spotify:track:1REh5aFdSnrw06A67wpGk3","spotify:track:0nXYmY9YtiHkFGlR3cusur","spotify:track:4cbN08AlbNtanvMNhPVcPe","spotify:track:72vuBPMhwFNlSYpTSf6fVD","spotify:track:7eQBzDRjBJ2bCkRKxNPbXm","spotify:track:0VBdCcaY6ERYKF7fZXQ8YX","spotify:track:4EWPO9rKRv0orDRlYLnn4J","spotify:track:3gJFL7cF0ziqTjqcIMNqv3"]},{"timestamp_utc":"2023-11-27T02:32:25.309Z","context_time":1701052345309,"message_context_uri":"spotify:playlist:37i9dQZEVXbkoSs7u90Cw1","message_is_made_for_user":true,"message_registration_country":"AE","message_track_uris":["spotify:track:0a2NP8kiyBjKMKr9yBgmu9","spotify:track:6i3DBbjAzfZqbnqCND1hlX","spotify:track:6c5GZseS9ToiFKoTKjUXPc","spotify:track:7993rSSJhvymBDhq0WeDeE","spotify:track:38jz2nov1xFBOzsNE60u4a","spotify:track:6vzZxRUs3Zxg0HuLoqtt6c","spotify:track:207YcqxaFYsOdJarlqyjWl","spotify:track:23DBeqyrFvncQFf9jiuklR","spotify:track:1MiFS7YNfRcJCiI8y33RUe","spotify:track:1qSLt4bauTRIlLo0lw1U02","spotify:track:27xsLWmSmEAiXABnOngOw7","spotify:track:5oT4UO1LJMgnl26aIy88ox","spotify:track:44PrLucPgjbVvMAjpvMDCk","spotify:track:1eKQFMKfCezCI1LF2oByEm","spotify:track:47IzfVVQs2orvksB1CGRvO","spotify:track:25jISSHAd4q2CVTsO7EHJM","spotify:track:0gkQiwGIuneO08yaQ68HK5","spotify:track:2jm0UrP5A9ccJ3twMI8cVq","spotify:track:4Q6S45dcKtAIBaGnGZ4yD6","spotify:track:1B8g9FFMUDXlCpjJfiiT9D","spotify:track:3HnpI9mWSRtOdHBrJxuUlD","spotify:track:4pAd9xohEcZ1NzQD3S14pP","spotify:track:5dRD4iHgRS4yKWCh2pdqUV","spotify:track:7FJ5LdspkWcxPUkV8dzMOL","spotify:track:322TvI9HYg7Tz2DizOAniw","spotify:track:2pgMykS4vRfWjCn3HBW7Sl","spotify:track:1anIxQ7F0J7Ayc9QMNwkNB","spotify:track:3duI7TT4kzLtoqf4PeUR3Z","spotify:track:7JJOUjiewemzvDXbq0LcBY","spotify:track:51h7YmJJp0FSM6AyFycRJ2"]},{"timestamp_utc":"2023-12-07T10:43:44.328Z","context_time":1701945824328,"message_context_uri":"spotify:playlist:37i9dQZEVXbkoSs7u90Cw1","message_is_made_for_user":true,"message_registration_country":"AE","message_track_uris":["spotify:track:7DTTBTO7kv7iqcOH3S9lC4","spotify:track:7eKrZvt4uORY0DLABy7gMY","spotify:track:1lvoAUC071648FyyvUjKLO","spotify:track:0TL0LFcwIBF5eX7arDIKxY","spotify:track:7lEQxb3JnTJcj2bHrP6kwH","spotify:track:4lYXywil8gd4a5shYzcJjP","spotify:track:1YzzGuqqfI71YEdNYPYIhO","spotify:track:0YxKKO272sacGBJKjf6FnB","spotify:track:4ApCig0GTR4IEp7Ijsyo3r","spotify:track:5lPlIrWYNLUwEJCSsI6hFi","spotify:track:0a2NP8kiyBjKMKr9yBgmu9","spotify:track:04odGx95cXda5ykFx7Pj6w","spotify:track:2WyStEQoQLEYH21xnCx1Th","spotify:track:7993rSSJhvymBDhq0WeDeE","spotify:track:38jz2nov1xFBOzsNE60u4a","spotify:track:6vzZxRUs3Zxg0HuLoqtt6c","spotify:track:207YcqxaFYsOdJarlqyjWl","spotify:track:23DBeqyrFvncQFf9jiuklR","spotify:track:4IDtPcFhlaarYWzn9H8Be5","spotify:track:40Ynf67EqlVgyu9tF4aNxE","spotify:track:7FmrM318GcKjV0qHIuAGci","spotify:track:3ejqftsE4bgYpjXWp3sfhO","spotify:track:1qSLt4bauTRIlLo0lw1U02","spotify:track:5oT4UO1LJMgnl26aIy88ox","spotify:track:44PrLucPgjbVvMAjpvMDCk","spotify:track:47IzfVVQs2orvksB1CGRvO","spotify:track:1eKQFMKfCezCI1LF2oByEm","spotify:track:0gkQiwGIuneO08yaQ68HK5","spotify:track:322TvI9HYg7Tz2DizOAniw","spotify:track:3duI7TT4kzLtoqf4PeUR3Z"]},{"timestamp_utc":"2024-01-31T17:59:15.619Z","context_time":1706723955619,"message_context_uri":"spotify:playlist:37i9dQZEVXbkoSs7u90Cw1","message_is_made_for_user":true,"message_registration_country":"AE","message_track_uris":["spotify:track:1QBMPnuR6v9OB1VVxgJB5G","spotify:track:1aooH2O4Y2neJ1aIZZOAml","spotify:track:047lJsrqwXM73t5a1iSF2B","spotify:track:0M0ANKNzmM4Odd7FNKghzW","spotify:track:6BfILljHPy6KB2W8Yp0Dr0","spotify:track:5eB2NeY2Px3EgzIsizedZe","spotify:track:3UxSyVzUrRxG3VyNNWWt7u","spotify:track:3wysCwuzcaaPGEibqnU3nz","spotify:track:2mtCcdlsA2q4CNzVWxlyxi","spotify:track:6F9zM0nqQE9OOsMGIPEQMD","spotify:track:6fMZ7g4JvGCRgLldIxi6Sl","spotify:track:5hzeUW4M10HRnSJyoQrH9x","spotify:track:7qn2DjVZipJEJ5h0p1HvSL","spotify:track:493n4dFutqZNQugLgPuQ1p","spotify:track:48TbjAwxnglZJzeEj7r3jv","spotify:track:7D6LiMiacu0gA5r299CxSp","spotify:track:0U8xGuKNtRz2PWVGaLjJ8V","spotify:track:4smqvcyz6mp27zNIUnLuvV","spotify:track:7lzPCtx5j2JRFhbsGpbzQ7","spotify:track:38uKHamvGkT14HDIGo5cOv","spotify:track:3EJslhR33350RLGMb6eOAg","spotify:track:1iB69nxVl29xhgqPQybrfY","spotify:track:2fIlZvbVnLBP5Q5nm4d1IN","spotify:track:0UldiKdMIMpWBxexAiEEen","spotify:track:4hOwZ6d11H6AKI5odjKTub","spotify:track:7zp98Ss6AfbryqI95507du","spotify:track:6BrZBHB0bQlCPJNZuuaqqu","spotify:track:49F2PdDfcTrVjACRPlsviv","spotify:track:2GsMrIHrRAkasLyhx3B4xN","spotify:track:387j61utwXNE7Bvi5UTR2k"]},{"timestamp_utc":"2024-02-05T04:31:51.140Z","context_time":1707107511140,"message_context_uri":"spotify:playlist:37i9dQZEVXbkoSs7u90Cw1","message_is_made_for_user":true,"message_registration_country":"AE","message_track_uris":["spotify:track:6PNhbEHabSERm2YHXOSizH","spotify:track:4m47o25mr9RqvOUzfRyjy3","spotify:track:2PCkD2ZI7zf0LOWdH2gNz5","spotify:track:5Msv4zzbXHxK0TzlAySK1J","spotify:track:5t36KLDvhjsIaat1DDxrDo","spotify:track:2usXJTfTSRH5ajx7uLnBfQ","spotify:track:2edUKbpj6GxgViPiL5EbIq","spotify:track:1QBMPnuR6v9OB1VVxgJB5G","spotify:track:1aooH2O4Y2neJ1aIZZOAml","spotify:track:047lJsrqwXM73t5a1iSF2B","spotify:track:6BfILljHPy6KB2W8Yp0Dr0","spotify:track:5eB2NeY2Px3EgzIsizedZe","spotify:track:3UxSyVzUrRxG3VyNNWWt7u","spotify:track:3wysCwuzcaaPGEibqnU3nz","spotify:track:2mtCcdlsA2q4CNzVWxlyxi","spotify:track:6F9zM0nqQE9OOsMGIPEQMD","spotify:track:6fMZ7g4JvGCRgLldIxi6Sl","spotify:track:753yGdIWiuZUn1cDRJziT7","spotify:track:6RaNwx66fRVaj07kZZWwV5","spotify:track:2IzKfxGPk9hbJdGJhZWIAb","spotify:track:5gPRX0AmXth8OKLJ0QuKae","spotify:track:7qn2DjVZipJEJ5h0p1HvSL","spotify:track:493n4dFutqZNQugLgPuQ1p","spotify:track:48TbjAwxnglZJzeEj7r3jv","spotify:track:0U8xGuKNtRz2PWVGaLjJ8V","spotify:track:4smqvcyz6mp27zNIUnLuvV","spotify:track:7lzPCtx5j2JRFhbsGpbzQ7","spotify:track:38uKHamvGkT14HDIGo5cOv","spotify:track:3EJslhR33350RLGMb6eOAg","spotify:track:387j61utwXNE7Bvi5UTR2k"]},{"timestamp_utc":"2023-12-15T20:43:05.707Z","context_time":1702672985707,"message_context_uri":"spotify:playlist:37i9dQZEVXbkoSs7u90Cw1","message_is_made_for_user":true,"message_registration_country":"AE","message_track_uris":["spotify:track:0Nz23ikouHjjqmw6VDMXA6","spotify:track:25yA3k7cBNDqejRJUun4Qe","spotify:track:74vhTmkzSXbNRlVe3dvsEw","spotify:track:0hN3gqhsyQryxyfUwbsAJY","spotify:track:2oVHoIWuMqI5NVz6WYn7Hz","spotify:track:5B8VpcIC3EAI3wke3XQoRy","spotify:track:5dvPoqBSwHiFR0uGBppPYQ","spotify:track:2PC92mpsc0XCCILU85Dlvz","spotify:track:3L5n8FHAe9RCsrKDSDbU0t","spotify:track:7nrVOGH5g2XbCcVIPc1z2v","spotify:track:74qIx2lHqfMB8SnlborPoG","spotify:track:3bWm8ejTzkMhPSdBnpxLvl","spotify:track:3QX2xbfH8LDUaHIA5YQmtO","spotify:track:4g8BvKyw10b20zfYS3LnoL","spotify:track:0jaX10A3R9z6iMdVrq6Xiz","spotify:track:4yagkb6nJCRcfjUhaOVHTw","spotify:track:4SmmoqGZXCido1Tcddy5cI","spotify:track:7smWOsdOrLqq87a8sRN0PH","spotify:track:7eKrZvt4uORY0DLABy7gMY","spotify:track:1lvoAUC071648FyyvUjKLO","spotify:track:7lEQxb3JnTJcj2bHrP6kwH","spotify:track:4lYXywil8gd4a5shYzcJjP","spotify:track:1YzzGuqqfI71YEdNYPYIhO","spotify:track:0a2NP8kiyBjKMKr9yBgmu9","spotify:track:7993rSSJhvymBDhq0WeDeE","spotify:track:38jz2nov1xFBOzsNE60u4a","spotify:track:6vzZxRUs3Zxg0HuLoqtt6c","spotify:track:04odGx95cXda5ykFx7Pj6w","spotify:track:1qSLt4bauTRIlLo0lw1U02","spotify:track:44PrLucPgjbVvMAjpvMDCk"]},{"timestamp_utc":"2023-12-08T15:09:14.517Z","context_time":1702048154517,"message_context_uri":"spotify:playlist:37i9dQZEVXbkoSs7u90Cw1","message_is_made_for_user":true,"message_registration_country":"AE","message_track_uris":["spotify:track:3L5n8FHAe9RCsrKDSDbU0t","spotify:track:7nrVOGH5g2XbCcVIPc1z2v","spotify:track:3bWm8ejTzkMhPSdBnpxLvl","spotify:track:3QX2xbfH8LDUaHIA5YQmtO","spotify:track:4g8BvKyw10b20zfYS3LnoL","spotify:track:0jaX10A3R9z6iMdVrq6Xiz","spotify:track:4yagkb6nJCRcfjUhaOVHTw","spotify:track:4SmmoqGZXCido1Tcddy5cI","spotify:track:7smWOsdOrLqq87a8sRN0PH","spotify:track:1Ma9rGhZMloUx9NEpTNYpF","spotify:track:7DTTBTO7kv7iqcOH3S9lC4","spotify:track:7eKrZvt4uORY0DLABy7gMY","spotify:track:1lvoAUC071648FyyvUjKLO","spotify:track:7lEQxb3JnTJcj2bHrP6kwH","spotify:track:4lYXywil8gd4a5shYzcJjP","spotify:track:1YzzGuqqfI71YEdNYPYIhO","spotify:track:0TL0LFcwIBF5eX7arDIKxY","spotify:track:7GHRy23VSudw3apSiBV5IF","spotify:track:4BGGZZnhsaQTxdnDxwzLSu","spotify:track:0a2NP8kiyBjKMKr9yBgmu9","spotify:track:7993rSSJhvymBDhq0WeDeE","spotify:track:38jz2nov1xFBOzsNE60u4a","spotify:track:6vzZxRUs3Zxg0HuLoqtt6c","spotify:track:04odGx95cXda5ykFx7Pj6w","spotify:track:1qSLt4bauTRIlLo0lw1U02","spotify:track:5oT4UO1LJMgnl26aIy88ox","spotify:track:44PrLucPgjbVvMAjpvMDCk","spotify:track:1eKQFMKfCezCI1LF2oByEm","spotify:track:322TvI9HYg7Tz2DizOAniw","spotify:track:3duI7TT4kzLtoqf4PeUR3Z"]},{"timestamp_utc":"2023-11-23T18:04:25.111Z","context_time":1700762665111,"message_context_uri":"spotify:playlist:37i9dQZEVXbkoSs7u90Cw1","message_is_made_for_user":true,"message_registration_country":"AE","message_track_uris":["spotify:track:1qSLt4bauTRIlLo0lw1U02","spotify:track:27xsLWmSmEAiXABnOngOw7","spotify:track:5oT4UO1LJMgnl26aIy88ox","spotify:track:1eKQFMKfCezCI1LF2oByEm","spotify:track:47IzfVVQs2orvksB1CGRvO","spotify:track:0gkQiwGIuneO08yaQ68HK5","spotify:track:4Q6S45dcKtAIBaGnGZ4yD6","spotify:track:0jqki4UKTXtSkyZjKiTUsi","spotify:track:7q8RDjLprHOErgwz4ReQGA","spotify:track:3ZzUOWnQuNxenx2MbZqtYq","spotify:track:50ISJbc0MNUxfzrhDg2k92","spotify:track:4m2af7wCfOyYLBQZ3l7xLs","spotify:track:0e9puAKZblpFaZyEZ0ZcJ6","spotify:track:322TvI9HYg7Tz2DizOAniw","spotify:track:2pgMykS4vRfWjCn3HBW7Sl","spotify:track:2m4s3761CzsYyH5lYoF4qu","spotify:track:1anIxQ7F0J7Ayc9QMNwkNB","spotify:track:2aj9isuH4NcbdNKJrOWMTs","spotify:track:0zboMHaQqZSc5g094rpR9j","spotify:track:5St1eVg5tOIK9HEmMJznLX","spotify:track:0Qo75eJMY72e5IQJt0Dz9z","spotify:track:0Q37Ax4ON1mIANcQvqfbOl","spotify:track:6qkwieeAuu97CLLtuooHd3","spotify:track:7JJOUjiewemzvDXbq0LcBY","spotify:track:51h7YmJJp0FSM6AyFycRJ2","spotify:track:6bpQvYciF8jtaaXrGV6AKp","spotify:track:3n3TDfjL4RD8sC8ZOakgkW","spotify:track:4bWN06wez00SFofUjnvLfG","spotify:track:6vPFDbyzSYWAL7r3Waa7BZ","spotify:track:3DNluh1hzpBIwIhMNAhN3V"]},{"timestamp_utc":"2023-11-17T02:59:49.707Z","context_time":1700189989707,"message_context_uri":"spotify:playlist:37i9dQZEVXbkoSs7u90Cw1","message_is_made_for_user":true,"message_registration_country":"AE","message_track_uris":["spotify:track:0qcfldI35P1RCX5OP0qwEC","spotify:track:27xsLWmSmEAiXABnOngOw7","spotify:track:5oT4UO1LJMgnl26aIy88ox","spotify:track:1eKQFMKfCezCI1LF2oByEm","spotify:track:47IzfVVQs2orvksB1CGRvO","spotify:track:3ZzUOWnQuNxenx2MbZqtYq","spotify:track:50ISJbc0MNUxfzrhDg2k92","spotify:track:0e9puAKZblpFaZyEZ0ZcJ6","spotify:track:322TvI9HYg7Tz2DizOAniw","spotify:track:2pgMykS4vRfWjCn3HBW7Sl","spotify:track:2m4s3761CzsYyH5lYoF4qu","spotify:track:1anIxQ7F0J7Ayc9QMNwkNB","spotify:track:11L6UdbFQFoNVW7gsDvIBY","spotify:track:5St1eVg5tOIK9HEmMJznLX","spotify:track:6qkwieeAuu97CLLtuooHd3","spotify:track:7JJOUjiewemzvDXbq0LcBY","spotify:track:51h7YmJJp0FSM6AyFycRJ2","spotify:track:6bpQvYciF8jtaaXrGV6AKp","spotify:track:3n3TDfjL4RD8sC8ZOakgkW","spotify:track:5JjWn73UGaWg2ybEk6xq2Y","spotify:track:4bWN06wez00SFofUjnvLfG","spotify:track:6vPFDbyzSYWAL7r3Waa7BZ","spotify:track:72DQsnQrsEwfgTgaqRzahu","spotify:track:6mhopOuZqV3ujE7oQ9T1tM","spotify:track:1DjLHxz1m4mzrov8p9BBZP","spotify:track:7mm2itQtTNqoGUK3G1QrSi","spotify:track:18NWRHrL2xqGIw5SGSyf3S","spotify:track:3DNluh1hzpBIwIhMNAhN3V","spotify:track:3YXhx1pJKA5YjMSMRV4D4J","spotify:track:6vB3eJU3ZOZXJxOKRcT2kl"]},{"timestamp_utc":"2023-12-06T02:46:09.631Z","context_time":1701830769631,"message_context_uri":"spotify:playlist:37i9dQZEVXbkoSs7u90Cw1","message_is_made_for_user":true,"message_registration_country":"AE","message_track_uris":["spotify:track:7DTTBTO7kv7iqcOH3S9lC4","spotify:track:7eKrZvt4uORY0DLABy7gMY","spotify:track:1lvoAUC071648FyyvUjKLO","spotify:track:0TL0LFcwIBF5eX7arDIKxY","spotify:track:7lEQxb3JnTJcj2bHrP6kwH","spotify:track:4lYXywil8gd4a5shYzcJjP","spotify:track:1YzzGuqqfI71YEdNYPYIhO","spotify:track:4ApCig0GTR4IEp7Ijsyo3r","spotify:track:0YxKKO272sacGBJKjf6FnB","spotify:track:5lPlIrWYNLUwEJCSsI6hFi","spotify:track:0a2NP8kiyBjKMKr9yBgmu9","spotify:track:04odGx95cXda5ykFx7Pj6w","spotify:track:2WyStEQoQLEYH21xnCx1Th","spotify:track:7993rSSJhvymBDhq0WeDeE","spotify:track:38jz2nov1xFBOzsNE60u4a","spotify:track:6vzZxRUs3Zxg0HuLoqtt6c","spotify:track:207YcqxaFYsOdJarlqyjWl","spotify:track:23DBeqyrFvncQFf9jiuklR","spotify:track:4IDtPcFhlaarYWzn9H8Be5","spotify:track:40Ynf67EqlVgyu9tF4aNxE","spotify:track:7FmrM318GcKjV0qHIuAGci","spotify:track:3ejqftsE4bgYpjXWp3sfhO","spotify:track:1qSLt4bauTRIlLo0lw1U02","spotify:track:5oT4UO1LJMgnl26aIy88ox","spotify:track:44PrLucPgjbVvMAjpvMDCk","spotify:track:47IzfVVQs2orvksB1CGRvO","spotify:track:1eKQFMKfCezCI1LF2oByEm","spotify:track:0gkQiwGIuneO08yaQ68HK5","spotify:track:322TvI9HYg7Tz2DizOAniw","spotify:track:3duI7TT4kzLtoqf4PeUR3Z"]},{"timestamp_utc":"2023-11-12T12:11:21.543Z","context_time":1699791081543,"message_context_uri":"spotify:playlist:37i9dQZEVXbkoSs7u90Cw1","message_is_made_for_user":true,"message_registration_country":"AE","message_track_uris":["spotify:track:65kga6DUIuueiZHR52tWcb","spotify:track:0Rs8QF1GrAar2X4pHRutmL","spotify:track:1anIxQ7F0J7Ayc9QMNwkNB","spotify:track:2pgMykS4vRfWjCn3HBW7Sl","spotify:track:2m4s3761CzsYyH5lYoF4qu","spotify:track:2FOzVtoTjalPbQpsvAVTTI","spotify:track:6qkwieeAuu97CLLtuooHd3","spotify:track:3n3TDfjL4RD8sC8ZOakgkW","spotify:track:6bpQvYciF8jtaaXrGV6AKp","spotify:track:6vPFDbyzSYWAL7r3Waa7BZ","spotify:track:3yHyiUDJdz02FZ6jfUbsmY","spotify:track:35ugbjNCcL0d39D1C5eyt4","spotify:track:18NWRHrL2xqGIw5SGSyf3S","spotify:track:6vB3eJU3ZOZXJxOKRcT2kl","spotify:track:3DNluh1hzpBIwIhMNAhN3V","spotify:track:1sZFDDmmBVkcHOpV6AB0Nx","spotify:track:5PlvEOKEO40fwk1qHXGuH0","spotify:track:6FahmzZYKH0zb2f9hrVsvw","spotify:track:2tb3BSK1Z9s5n7YynbuAbp","spotify:track:6SfLZ94X4nImZChgqmoP3q","spotify:track:1REh5aFdSnrw06A67wpGk3","spotify:track:0i7hmzHYai87aZzlKT7MhO","spotify:track:6p8DwAh6wJ7S6jmpyYlBYp","spotify:track:4cbN08AlbNtanvMNhPVcPe","spotify:track:0nXYmY9YtiHkFGlR3cusur","spotify:track:72vuBPMhwFNlSYpTSf6fVD","spotify:track:7eQBzDRjBJ2bCkRKxNPbXm","spotify:track:0VBdCcaY6ERYKF7fZXQ8YX","spotify:track:4EWPO9rKRv0orDRlYLnn4J","spotify:track:3gJFL7cF0ziqTjqcIMNqv3"]},{"timestamp_utc":"2023-11-13T10:07:29.325Z","context_time":1699870049325,"message_context_uri":"spotify:playlist:37i9dQZEVXbkoSs7u90Cw1","message_is_made_for_user":true,"message_registration_country":"AE","message_track_uris":["spotify:track:65kga6DUIuueiZHR52tWcb","spotify:track:0Rs8QF1GrAar2X4pHRutmL","spotify:track:1anIxQ7F0J7Ayc9QMNwkNB","spotify:track:2pgMykS4vRfWjCn3HBW7Sl","spotify:track:2m4s3761CzsYyH5lYoF4qu","spotify:track:2FOzVtoTjalPbQpsvAVTTI","spotify:track:6qkwieeAuu97CLLtuooHd3","spotify:track:3n3TDfjL4RD8sC8ZOakgkW","spotify:track:6bpQvYciF8jtaaXrGV6AKp","spotify:track:6vPFDbyzSYWAL7r3Waa7BZ","spotify:track:3yHyiUDJdz02FZ6jfUbsmY","spotify:track:35ugbjNCcL0d39D1C5eyt4","spotify:track:18NWRHrL2xqGIw5SGSyf3S","spotify:track:6vB3eJU3ZOZXJxOKRcT2kl","spotify:track:3DNluh1hzpBIwIhMNAhN3V","spotify:track:1sZFDDmmBVkcHOpV6AB0Nx","spotify:track:6FahmzZYKH0zb2f9hrVsvw","spotify:track:5PlvEOKEO40fwk1qHXGuH0","spotify:track:2tb3BSK1Z9s5n7YynbuAbp","spotify:track:6SfLZ94X4nImZChgqmoP3q","spotify:track:0i7hmzHYai87aZzlKT7MhO","spotify:track:1REh5aFdSnrw06A67wpGk3","spotify:track:6p8DwAh6wJ7S6jmpyYlBYp","spotify:track:4cbN08AlbNtanvMNhPVcPe","spotify:track:0nXYmY9YtiHkFGlR3cusur","spotify:track:72vuBPMhwFNlSYpTSf6fVD","spotify:track:7eQBzDRjBJ2bCkRKxNPbXm","spotify:track:0VBdCcaY6ERYKF7fZXQ8YX","spotify:track:4EWPO9rKRv0orDRlYLnn4J","spotify:track:3gJFL7cF0ziqTjqcIMNqv3"]},{"timestamp_utc":"2023-11-28T18:45:29.661Z","context_time":1701197129661,"message_context_uri":"spotify:playlist:37i9dQZEVXbkoSs7u90Cw1","message_is_made_for_user":true,"message_registration_country":"AE","message_track_uris":["spotify:track:0a2NP8kiyBjKMKr9yBgmu9","spotify:track:6i3DBbjAzfZqbnqCND1hlX","spotify:track:04odGx95cXda5ykFx7Pj6w","spotify:track:7993rSSJhvymBDhq0WeDeE","spotify:track:38jz2nov1xFBOzsNE60u4a","spotify:track:6vzZxRUs3Zxg0HuLoqtt6c","spotify:track:207YcqxaFYsOdJarlqyjWl","spotify:track:23DBeqyrFvncQFf9jiuklR","spotify:track:1MiFS7YNfRcJCiI8y33RUe","spotify:track:1qSLt4bauTRIlLo0lw1U02","spotify:track:27xsLWmSmEAiXABnOngOw7","spotify:track:5oT4UO1LJMgnl26aIy88ox","spotify:track:44PrLucPgjbVvMAjpvMDCk","spotify:track:1eKQFMKfCezCI1LF2oByEm","spotify:track:47IzfVVQs2orvksB1CGRvO","spotify:track:25jISSHAd4q2CVTsO7EHJM","spotify:track:0gkQiwGIuneO08yaQ68HK5","spotify:track:4U5RcowtVHV0S9QqfxKPs7","spotify:track:2jm0UrP5A9ccJ3twMI8cVq","spotify:track:4Q6S45dcKtAIBaGnGZ4yD6","spotify:track:1B8g9FFMUDXlCpjJfiiT9D","spotify:track:4pAd9xohEcZ1NzQD3S14pP","spotify:track:7FJ5LdspkWcxPUkV8dzMOL","spotify:track:5dRD4iHgRS4yKWCh2pdqUV","spotify:track:322TvI9HYg7Tz2DizOAniw","spotify:track:2pgMykS4vRfWjCn3HBW7Sl","spotify:track:1anIxQ7F0J7Ayc9QMNwkNB","spotify:track:3duI7TT4kzLtoqf4PeUR3Z","spotify:track:7JJOUjiewemzvDXbq0LcBY","spotify:track:51h7YmJJp0FSM6AyFycRJ2"]},{"timestamp_utc":"2024-01-21T04:20:26.713Z","context_time":1705810826713,"message_context_uri":"spotify:playlist:37i9dQZEVXbkoSs7u90Cw1","message_is_made_for_user":true,"message_registration_country":"AE","message_track_uris":["spotify:track:7qn2DjVZipJEJ5h0p1HvSL","spotify:track:493n4dFutqZNQugLgPuQ1p","spotify:track:48TbjAwxnglZJzeEj7r3jv","spotify:track:6nbd9EhZimtWBkKgKeURqI","spotify:track:7D6LiMiacu0gA5r299CxSp","spotify:track:4smqvcyz6mp27zNIUnLuvV","spotify:track:7lzPCtx5j2JRFhbsGpbzQ7","spotify:track:76KVwRKhtalBUdhAM7MRYb","spotify:track:38uKHamvGkT14HDIGo5cOv","spotify:track:3EJslhR33350RLGMb6eOAg","spotify:track:1iB69nxVl29xhgqPQybrfY","spotify:track:2fIlZvbVnLBP5Q5nm4d1IN","spotify:track:31nuv0YPbdyAZgmEgkerlT","spotify:track:3NNKHTBzQZAHX8EkcqKcK3","spotify:track:387j61utwXNE7Bvi5UTR2k","spotify:track:0ifLfKVPTV1vHjfI0JThNR","spotify:track:1Mk4uWL6Lm8J6nz4WQET91","spotify:track:0jEUKF976XF6uIQRkkrfrs","spotify:track:1lcvcBmvmgjSfSxYyn8N1e","spotify:track:0OqVP6TzR9G0xiuFi5dG8T","spotify:track:7eV34n7iW2P2keihlEsFRh","spotify:track:3FlD8BkjHhe7sWmnZU00E0","spotify:track:6HBl5AiLPw1nzAYz2fZPjD","spotify:track:5H2kdYFqR1ZYhLjkqSvoWz","spotify:track:4bYablkjuG0CbBvfKOlVBA","spotify:track:5aeXimPjlHeqI7W7hJIqlo","spotify:track:1NMYbsFZyxwHRNaLGzFGWh","spotify:track:48H87I4tgT2V5n7ZDYXGPn","spotify:track:11p0NvJaWUuVdXBJ79Y8gj","spotify:track:2DaPCl392tphoi2TqslBdG"]},{"timestamp_utc":"2023-11-25T09:07:49.032Z","context_time":1700903269032,"message_context_uri":"spotify:playlist:37i9dQZEVXbkoSs7u90Cw1","message_is_made_for_user":true,"message_registration_country":"AE","message_track_uris":["spotify:track:0a2NP8kiyBjKMKr9yBgmu9","spotify:track:6i3DBbjAzfZqbnqCND1hlX","spotify:track:04odGx95cXda5ykFx7Pj6w","spotify:track:7993rSSJhvymBDhq0WeDeE","spotify:track:38jz2nov1xFBOzsNE60u4a","spotify:track:6vzZxRUs3Zxg0HuLoqtt6c","spotify:track:207YcqxaFYsOdJarlqyjWl","spotify:track:23DBeqyrFvncQFf9jiuklR","spotify:track:1MiFS7YNfRcJCiI8y33RUe","spotify:track:1qSLt4bauTRIlLo0lw1U02","spotify:track:27xsLWmSmEAiXABnOngOw7","spotify:track:5oT4UO1LJMgnl26aIy88ox","spotify:track:44PrLucPgjbVvMAjpvMDCk","spotify:track:1eKQFMKfCezCI1LF2oByEm","spotify:track:47IzfVVQs2orvksB1CGRvO","spotify:track:25jISSHAd4q2CVTsO7EHJM","spotify:track:0gkQiwGIuneO08yaQ68HK5","spotify:track:4U5RcowtVHV0S9QqfxKPs7","spotify:track:2Fe9EBbXcPYB9q5yX0GSca","spotify:track:4Q6S45dcKtAIBaGnGZ4yD6","spotify:track:2jm0UrP5A9ccJ3twMI8cVq","spotify:track:1B8g9FFMUDXlCpjJfiiT9D","spotify:track:7FJ5LdspkWcxPUkV8dzMOL","spotify:track:322TvI9HYg7Tz2DizOAniw","spotify:track:2pgMykS4vRfWjCn3HBW7Sl","spotify:track:1anIxQ7F0J7Ayc9QMNwkNB","spotify:track:3duI7TT4kzLtoqf4PeUR3Z","spotify:track:7JJOUjiewemzvDXbq0LcBY","spotify:track:51h7YmJJp0FSM6AyFycRJ2","spotify:track:3n3TDfjL4RD8sC8ZOakgkW"]},{"timestamp_utc":"2023-11-24T05:50:04.850Z","context_time":1700805004850,"message_context_uri":"spotify:playlist:37i9dQZEVXbkoSs7u90Cw1","message_is_made_for_user":true,"message_registration_country":"AE","message_track_uris":["spotify:track:0a2NP8kiyBjKMKr9yBgmu9","spotify:track:6i3DBbjAzfZqbnqCND1hlX","spotify:track:6c5GZseS9ToiFKoTKjUXPc","spotify:track:7993rSSJhvymBDhq0WeDeE","spotify:track:38jz2nov1xFBOzsNE60u4a","spotify:track:6vzZxRUs3Zxg0HuLoqtt6c","spotify:track:207YcqxaFYsOdJarlqyjWl","spotify:track:23DBeqyrFvncQFf9jiuklR","spotify:track:1MiFS7YNfRcJCiI8y33RUe","spotify:track:1qSLt4bauTRIlLo0lw1U02","spotify:track:27xsLWmSmEAiXABnOngOw7","spotify:track:5oT4UO1LJMgnl26aIy88ox","spotify:track:44PrLucPgjbVvMAjpvMDCk","spotify:track:1eKQFMKfCezCI1LF2oByEm","spotify:track:47IzfVVQs2orvksB1CGRvO","spotify:track:25jISSHAd4q2CVTsO7EHJM","spotify:track:0gkQiwGIuneO08yaQ68HK5","spotify:track:4U5RcowtVHV0S9QqfxKPs7","spotify:track:2Fe9EBbXcPYB9q5yX0GSca","spotify:track:4Q6S45dcKtAIBaGnGZ4yD6","spotify:track:2jm0UrP5A9ccJ3twMI8cVq","spotify:track:1B8g9FFMUDXlCpjJfiiT9D","spotify:track:7FJ5LdspkWcxPUkV8dzMOL","spotify:track:322TvI9HYg7Tz2DizOAniw","spotify:track:2pgMykS4vRfWjCn3HBW7Sl","spotify:track:1anIxQ7F0J7Ayc9QMNwkNB","spotify:track:3duI7TT4kzLtoqf4PeUR3Z","spotify:track:7JJOUjiewemzvDXbq0LcBY","spotify:track:51h7YmJJp0FSM6AyFycRJ2","spotify:track:3n3TDfjL4RD8sC8ZOakgkW"]},{"timestamp_utc":"2023-11-16T02:21:55.266Z","context_time":1700101315266,"message_context_uri":"spotify:playlist:37i9dQZEVXbkoSs7u90Cw1","message_is_made_for_user":true,"message_registration_country":"AE","message_track_uris":["spotify:track:1eKQFMKfCezCI1LF2oByEm","spotify:track:0e9puAKZblpFaZyEZ0ZcJ6","spotify:track:322TvI9HYg7Tz2DizOAniw","spotify:track:65kga6DUIuueiZHR52tWcb","spotify:track:1anIxQ7F0J7Ayc9QMNwkNB","spotify:track:2pgMykS4vRfWjCn3HBW7Sl","spotify:track:2m4s3761CzsYyH5lYoF4qu","spotify:track:6qkwieeAuu97CLLtuooHd3","spotify:track:3n3TDfjL4RD8sC8ZOakgkW","spotify:track:6bpQvYciF8jtaaXrGV6AKp","spotify:track:3yHyiUDJdz02FZ6jfUbsmY","spotify:track:6vPFDbyzSYWAL7r3Waa7BZ","spotify:track:35ugbjNCcL0d39D1C5eyt4","spotify:track:18NWRHrL2xqGIw5SGSyf3S","spotify:track:6vB3eJU3ZOZXJxOKRcT2kl","spotify:track:3DNluh1hzpBIwIhMNAhN3V","spotify:track:1sZFDDmmBVkcHOpV6AB0Nx","spotify:track:5PlvEOKEO40fwk1qHXGuH0","spotify:track:6FahmzZYKH0zb2f9hrVsvw","spotify:track:6SfLZ94X4nImZChgqmoP3q","spotify:track:2tb3BSK1Z9s5n7YynbuAbp","spotify:track:0i7hmzHYai87aZzlKT7MhO","spotify:track:6p8DwAh6wJ7S6jmpyYlBYp","spotify:track:4cbN08AlbNtanvMNhPVcPe","spotify:track:0nXYmY9YtiHkFGlR3cusur","spotify:track:72vuBPMhwFNlSYpTSf6fVD","spotify:track:1REh5aFdSnrw06A67wpGk3","spotify:track:7eQBzDRjBJ2bCkRKxNPbXm","spotify:track:3gJFL7cF0ziqTjqcIMNqv3","spotify:track:6sQNYW4YycsO1c8uhZpdA2"]}]